Workbook
Name CROF: 'Question Detail'!$H$57:$H$66
Name DER_CC: 'Question Detail'!$H$46:$H$56
Name DER_System_Services: 'Question Detail'!$H$31:$H$45
Name IBR: 'Question Detail'!$H$2:$H$16
Name Planning: 'Question Detail'!$H$80:$H$100
Name Stability: 'Question Detail'!$H$17:$H$30
Name System_Services: 'Question Detail'!$H$67:$H$79

Sheet Template
A1: Abstract_Index | B1: 1
A2: Document Title | B2: Scenario Reduction Network Based on Wasserstein Distance With Regularization
A3: Abstract | B3: Power systems with high penetration of renewable energy contain various uncertainties. Scenario-based optimization problems need a large number of discrete scenarios to obtain a reliable approximation for the probabilistic model. It is important to choose typical scenarios and ease the computational burden. This paper presents a scenario reduction network model based on Wasserstein distance. Entropy regularization is used to transform the scenario reduction problem into an unconstrained problem. Through an explicit neural network structure design, the output of the scenario reduction network corresponds to the Sinkhorn distance function. The scenario reduction network can generate the typical scenario set through unsupervised learning. An efficient algorithm is proposed for continuous/discrete scenario reduction. The superiority of the scenario reduction network model is verified through case studies. The numerical results highlight the high accuracy and computational efficiency of the proposed model over state-of-the-art models, and it makes an ideal candidate for large-scale scenario reduction problems.
A4: Main Program | B4: Other | C4: Score [0-5] | D4: Rationale | F4: Instructions: 1) Only modify colored cells. 2) Select the main program. 3) Evaluate all questions in the list. 4) Evaluate affinity score with integers 0, 1, 2, 3, 4, and 5 according to the scale below. 5) Provide a rationale for at least two low-, two medium-, and two high-classified questions. Prioritise questions where the classification was particularly difficult, uncertain, or ambiguous. Affinity Scale: Low ∎ 0: No conceptual overlap. The abstract addresses a completely different topic, phenomenon or research domain. There are no shared concepts, methods, or outcomes. Any superficial keyword match is coincidental. The abstract would not appear in a literature review for this question under any reasonable interpretation. ∎ 1: Marginal overlap. One or two terms or concepts are shared but the abstract investigates a fundamentally different question. The research domain may be adjacent but the objectives, topic, or outcomes are misaligned. Findings from this abstract could not be used to inform an answer to the question even partially. A reader would not cite this abstract as background for the question. Moderate ∎ 2: Contextual overlap. The abstract shares the general domain and studies a related concept or phenomenon, but targets a different outcome, phenomenon, or objective. The abstract provides useful background or framing but cannot directly answer the question. A reader might cite it to establish context but not as evidence. ∎ 3: Partial evidence. The abstract addresses the same research objective as the question but in a different area, context, or with a different methodological framework. Findings are relevant but require adaptation or extrapolation to apply to the question. A reader would cite this abstract as indirect or supporting evidence, not as a primary source. High ∎ 4: Direct relevance. The abstract addresses the same question, phenomenon, and outcome. Minor differences in methodology, setting, or scope exist but do not prevent the findings from being directly applicable. A reader would cite this abstract as substantive evidence for answering the question. ∎ 5: Near-perfect match. The abstract is a primary source for the question. It addresses the same research question, phenomenon, outcome, and methodology with only incidental differences. A reader would consider this abstract central to any literature review on the question.
A5: Question | B5: {=INDIRECT(B4)} -> #REF!

Sheet Batch 1
A1: Abstract_Index | B1: ='Abstracts List'!A2 -> 1
A2: Document Title | B2: ='Abstracts List'!B2 -> Scenario Reduction Network Based on Wasserstein Distance With Regularization
A3: Abstract | B3: ='Abstracts List'!C2 -> Power systems with high penetration of renewable energy contain various uncertainties. Scenario-based optimization problems need a large number of discrete scenarios to obtain a reliable approximation for the probabilistic model. It is important to choose typical scenarios and ease the computational burden. This paper presents a scenario reduction network model based on Wasserstein distance. Entropy regularization is used to transform the scenario reduction problem into an unconstrained problem. Through an explicit neural network structure design, the output of the scenario reduction network corresponds to the Sinkhorn distance function. The scenario reduction network can generate the typical scenario set through unsupervised learning. An efficient algorithm is proposed for continuous/discrete scenario reduction. The superiority of the scenario reduction network model is verified through case studies. The numerical results highlight the high accuracy and computational efficiency of the proposed model over state-of-the-art models, and it makes an ideal candidate for large-scale scenario reduction problems.
A4: Main Program | B4: Planning | C4: Score [0-5] | D4: Rationale | F4: Instructions: 1) Only modify colored cells. 2) Select the main program. 3) Evaluate all questions in the list. 4) Evaluate affinity score with integers 0, 1, 2, 3, 4, and 5 according to the scale below. 5) Provide a rationale for at least two low-, two medium-, and two high-classified questions. Prioritise questions where the classification was particularly difficult, uncertain, or ambiguous. Affinity Scale: Low ∎ 0: No conceptual overlap. The abstract addresses a completely different topic, phenomenon or research domain. There are no shared concepts, methods, or outcomes. Any superficial keyword match is coincidental. The abstract would not appear in a literature review for this question under any reasonable interpretation. ∎ 1: Marginal overlap. One or two terms or concepts are shared but the abstract investigates a fundamentally different question. The research domain may be adjacent but the objectives, topic, or outcomes are misaligned. Findings from this abstract could not be used to inform an answer to the question even partially. A reader would not cite this abstract as background for the question. Moderate ∎ 2: Contextual overlap. The abstract shares the general domain and studies a related concept or phenomenon, but targets a different outcome, phenomenon, or objective. The abstract provides useful background or framing but cannot directly answer the question. A reader might cite it to establish context but not as evidence. ∎ 3: Partial evidence. The abstract addresses the same research objective as the question but in a different area, context, or with a different methodological framework. Findings are relevant but require adaptation or extrapolation to apply to the question. A reader would cite this abstract as indirect or supporting evidence, not as a primary source. High ∎ 4: Direct relevance. The abstract addresses the same question, phenomenon, and outcome. Minor differences in methodology, setting, or scope exist but do not prevent the findings from being directly applicable. A reader would cite this abstract as substantive evidence for answering the question. ∎ 5: Near-perfect match. The abstract is a primary source for the question. It addresses the same research question, phenomenon, outcome, and methodology with only incidental differences. A reader would consider this abstract central to any literature review on the question.
A5: Question | B5: {=INDIRECT(B4)} -> 12 - What mechanisms and appropriate aggregate DER representations and data are necessary to account for DERs in system-wide operation and planning, and in techno economic evaluation?
B6: 13 - How can system operators quantify the bulk-level energy and service opportunities from DER, and how can these services be shared among distribution operators, bulk operators, aggregators and (where applicable) customers?
B7: 14 - How can bulk-level services provided by DER be valued as a compromise between simplicity and, for example, a complex full cost-reflective approach?
B8: 27 - How can risk-based methods (e.g. probabilistic forecasting techniques) be better incorporated into operational decision-support tools and used consistently across multiple stages (e.g., real-time, day ahead, intraday planning)?
B9: 32 - How should system restoration services be structured and organized in systems with few or no synchronous machines, relying on IBR technologies and variable energy resources?
B10: 33 - How should the definitions of services for IBR-dominated grids be structured and can standard services and standard characteristics be defined as reasonable for large and small IBRs and across variable renewable energy, storage, demand response interfaces and for differing procurement mechanisms?
B11: 34 - What methods could determine the need, sufficiency, and locational nature of IBR voltage control and system strength services for a given area?
B12: 35 - What models and methods, including testing, are necessary to quantify the ability of variable renewable energy to provide essential reliability services to the grid, and how do system operators quantify the value of these reliability services (for example, as an input to system-specific market/incentive design questions)?
B13: 36 - What system services can be designed to enable response from IBRs that can be a substitute for inertia (i.e. very fast frequency response)?
B14: 37 - What studies and metrics are required to identify long-term scarcity of resources (capacity, energy, flexibility etc.) to maintain reliability?
B15: 38 - How should grid enhancing technologies be included in the planning processes?
B16: 39 - What technical models need to be added to long-term planning methods and studies to consider other reliability services in addition to traditional resource adequacy and deliverability? For example, how should sufficient restoration capability be modeled in long-term reliability studies?
B17: 40 - What studies and metrics are required to evaluate resource adequacy with hybrid plants (e.g., photovoltaics-plus-storage) and virtual power plants?
... B25: 48 - What additional planning models and methods are needed to plan for a system that can withstand expected or unexpected lulls (e.g., an extended wind drought, or a dunkelflaute)?
A28: Abstract_Index | B28: ='Abstracts List'!A3 -> 103
A29: Document Title | B29: ='Abstracts List'!B3 -> Characteristic Investigation and Overvoltage Suppression of MMC-HVDC Integrated Offshore Wind Farms Under Onshore Valve-Side SPG Fault
A30: Abstract | B30: ='Abstracts List'!C3 -> The valve-side ground fault in the converter station of modular multilevel converter based high voltage direct current (MMC-HVDC) is a serious threat to the security of power systems. Hence, this paper analyzes the most common single-phase-to-ground (SPG) fault characteristics of valve-side faults in onshore converter stations of MMC-HVDC integrated offshore wind farms. The propagation and impact mechanism of onshore SPG fault to offshore HVDC transmission lines, offshore converter station, and wind farms are deduced based on the MMC control principle. Furthermore, an overvoltage suppression strategy based on zero-sequence voltage modulation is proposed. The effect mechanism of this strategy on the transient stability of the system is analyzed. The key parameter of the proposed strategy is also designed considering both the practical engineering requirements and the impact of the system operation. Finally, the theoretical analysis of fault characteristics and the proposed overvoltage suppression strategy are verified by the PSCAD/EMTDC simulation platform. Simulation results not only show good agreement with the theoretical analysis of the fault characteristics, but also prove the effectiveness of the proposed overvoltage suppression strategy.
A31: Main Program | B31: Other | C31: Score [0-5] | D31: Rationale | F31: Instructions: 1) Only modify colored cells. 2) Select the main program. 3) Evaluate all questions in the list. 4) Evaluate affinity score with integers 0, 1, 2, 3, 4, and 5 according to the scale below. 5) Provide a rationale for at least two low-, two medium-, and two high-classified questions. Prioritise questions where the classification was particularly difficult, uncertain, or ambiguous. Affinity Scale: Low ∎ 0: No conceptual overlap. The abstract addresses a completely different topic, phenomenon or research domain. There are no shared concepts, methods, or outcomes. Any superficial keyword match is coincidental. The abstract would not appear in a literature review for this question under any reasonable interpretation. ∎ 1: Marginal overlap. One or two terms or concepts are shared but the abstract investigates a fundamentally different question. The research domain may be adjacent but the objectives, topic, or outcomes are misaligned. Findings from this abstract could not be used to inform an answer to the question even partially. A reader would not cite this abstract as background for the question. Moderate ∎ 2: Contextual overlap. The abstract shares the general domain and studies a related concept or phenomenon, but targets a different outcome, phenomenon, or objective. The abstract provides useful background or framing but cannot directly answer the question. A reader might cite it to establish context but not as evidence. ∎ 3: Partial evidence. The abstract addresses the same research objective as the question but in a different area, context, or with a different methodological framework. Findings are relevant but require adaptation or extrapolation to apply to the question. A reader would cite this abstract as indirect or supporting evidence, not as a primary source. High ∎ 4: Direct relevance. The abstract addresses the same question, phenomenon, and outcome. Minor differences in methodology, setting, or scope exist but do not prevent the findings from being directly applicable. A reader would cite this abstract as substantive evidence for answering the question. ∎ 5: Near-perfect match. The abstract is a primary source for the question. It addresses the same research question, phenomenon, outcome, and methodology with only incidental differences. A reader would consider this abstract central to any literature review on the question.
A32: Question | B32: {=INDIRECT(B31)} -> #REF!
A55: Abstract_Index | B55: ='Abstracts List'!A4 -> 115
A56: Document Title | B56: ='Abstracts List'!B4 -> Adaptive Stability Contingency Screening for Operational Planning Based on Domain-Adversarial Graph Neural Network
A57: Abstract | B57: ='Abstracts List'!C4 -> Compared to contingency screening (CS) techniques that focus on thermal/voltage limit violation, CS that addresses the transient and small-signal stability contingencies in the existing references requires a higher computational cost, limiting its use to off-line contingency analysis. Therefore, it poses the challenge of developing an effective CS scheme for fast recognition of critical contingency, which is one of the major concerns of system operators. To deal with this problem, this article proposes an adaptive stability CS (SCS) scheme for operational planning. One challenge in developing the adaptive SCS for different cardinal points is data distribution discrepancy resulted from load/topology changes. To align data distribution between different domains (i.e., cardinal points), a domain-adversarial graph neural network (DAGNN) is developed to learn the domain-invariant features, so that the DAGNN model trained on the labeled source domain (e.g., peak cardinal point 2B) data can be applied to the unlabeled target domain (e.g., trough cardinal point 1B) data for SCS. To make the proposed SCS more efficient in dealing with power system data, a graph learning approach combined with graph transformer and graph isomorphism network is used in DAGNN to provide feature representations considering the graph properties of power systems, where nodes and edges refer to buses and transmission lines, respectively. Experiments on IEEE 39 Bus system and IEEE 118 Bus system have verified the effectiveness of the proposed model.
A58: Main Program | B58: Other | C58: Score [0-5] | D58: Rationale | F58: Instructions: 1) Only modify colored cells. 2) Select the main program. 3) Evaluate all questions in the list. 4) Evaluate affinity score with integers 0, 1, 2, 3, 4, and 5 according to the scale below. 5) Provide a rationale for at least two low-, two medium-, and two high-classified questions. Prioritise questions where the classification was particularly difficult, uncertain, or ambiguous. Affinity Scale: Low ∎ 0: No conceptual overlap. The abstract addresses a completely different topic, phenomenon or research domain. There are no shared concepts, methods, or outcomes. Any superficial keyword match is coincidental. The abstract would not appear in a literature review for this question under any reasonable interpretation. ∎ 1: Marginal overlap. One or two terms or concepts are shared but the abstract investigates a fundamentally different question. The research domain may be adjacent but the objectives, topic, or outcomes are misaligned. Findings from this abstract could not be used to inform an answer to the question even partially. A reader would not cite this abstract as background for the question. Moderate ∎ 2: Contextual overlap. The abstract shares the general domain and studies a related concept or phenomenon, but targets a different outcome, phenomenon, or objective. The abstract provides useful background or framing but cannot directly answer the question. A reader might cite it to establish context but not as evidence. ∎ 3: Partial evidence. The abstract addresses the same research objective as the question but in a different area, context, or with a different methodological framework. Findings are relevant but require adaptation or extrapolation to apply to the question. A reader would cite this abstract as indirect or supporting evidence, not as a primary source. High ∎ 4: Direct relevance. The abstract addresses the same question, phenomenon, and outcome. Minor differences in methodology, setting, or scope exist but do not prevent the findings from being directly applicable. A reader would cite this abstract as substantive evidence for answering the question. ∎ 5: Near-perfect match. The abstract is a primary source for the question. It addresses the same research question, phenomenon, outcome, and methodology with only incidental differences. A reader would consider this abstract central to any literature review on the question.
A59: Question | B59: {=INDIRECT(B58)} -> #REF!
A82: Abstract_Index | B82: ='Abstracts List'!A5 -> 81
A83: Document Title | B83: ='Abstracts List'!B5 -> Virtual Prosumers P2P Transaction Based Distribution Network Expansion Planning
A84: Abstract | B84: ='Abstracts List'!C5 -> The deployment of prosumers with distributed energy resources (DERs) has facilitated the prosumer-centric transactive market, giving rise to the consequent necessity for the coordination between prosumers and the distribution networks. This paper proposes an incentive-based expansion planning method considering virtual peer-to-peer (P2P) transaction among prosumers, which is characterized as a tri-level planning-operation-transaction framework. Each prosumer optimizes its internal response of DERs and external P2P transaction jointly, formulating virtual P2P transaction. Under such a paradigm, the distribution company (DISCO) identifies the optimal expansion planning in the network assets, while the independent distribution system operator (IDSO) is responsible for the optimal operation of the expanded distribution networks. To derive appropriate incentives for each prosumer, the DISCO and IDSO allocate long-term investment network charges and short-term operation network charges on prosumers, along with the designed financial transmission rights coupling multiple time scales. Through such incentives, self-profit driven virtual transactions can relieve operation problems and postpone expansion planning, acting as a short-term alternative. Moreover, a risk-based approach is proposed for prosumer to flexibly change strategy according to different risk preference. Finally, results from the case study demonstrate the superiority and effectiveness of the proposed method in the collaborative application of virtual transaction in the expansion planning.
A85: Main Program | B85: Other | C85: Score [0-5] | D85: Rationale | F85: Instructions: 1) Only modify colored cells. 2) Select the main program. 3) Evaluate all questions in the list. 4) Evaluate affinity score with integers 0, 1, 2, 3, 4, and 5 according to the scale below. 5) Provide a rationale for at least two low-, two medium-, and two high-classified questions. Prioritise questions where the classification was particularly difficult, uncertain, or ambiguous. Affinity Scale: Low ∎ 0: No conceptual overlap. The abstract addresses a completely different topic, phenomenon or research domain. There are no shared concepts, methods, or outcomes. Any superficial keyword match is coincidental. The abstract would not appear in a literature review for this question under any reasonable interpretation. ∎ 1: Marginal overlap. One or two terms or concepts are shared but the abstract investigates a fundamentally different question. The research domain may be adjacent but the objectives, topic, or outcomes are misaligned. Findings from this abstract could not be used to inform an answer to the question even partially. A reader would not cite this abstract as background for the question. Moderate ∎ 2: Contextual overlap. The abstract shares the general domain and studies a related concept or phenomenon, but targets a different outcome, phenomenon, or objective. The abstract provides useful background or framing but cannot directly answer the question. A reader might cite it to establish context but not as evidence. ∎ 3: Partial evidence. The abstract addresses the same research objective as the question but in a different area, context, or with a different methodological framework. Findings are relevant but require adaptation or extrapolation to apply to the question. A reader would cite this abstract as indirect or supporting evidence, not as a primary source. High ∎ 4: Direct relevance. The abstract addresses the same question, phenomenon, and outcome. Minor differences in methodology, setting, or scope exist but do not prevent the findings from being directly applicable. A reader would cite this abstract as substantive evidence for answering the question. ∎ 5: Near-perfect match. The abstract is a primary source for the question. It addresses the same research question, phenomenon, outcome, and methodology with only incidental differences. A reader would consider this abstract central to any literature review on the question.
A86: Question | B86: {=INDIRECT(B85)} -> #REF!
A109: Abstract_Index | B109: ='Abstracts List'!A6 -> 134
A110: Document Title | B110: ='Abstracts List'!B6 -> High-Dimensional Feature Selection for Power System Congestion Event Prognosis With Enhanced Evolutionary Computation
A111: Abstract | B111: ='Abstracts List'!C6 -> Power system congestion event prognosis (CEP) based on multivariate time series (MTS) learning is an effective way to improve the warning abilities against risky situations. However, it is still challenging to decide which measurement sequences of system variables should be selected to train MTS learning-based CEPs models, especially when facing high-dimensional candidate features from power systems. Focusing on this issue, this paper proposes a novel high-dimensional feature selection (FS) method to identify and select variables that contain beneficial data patterns for the prognosis of network congestion events. A wrapper framework embedded with multiple MTS learning models is first built to treat FS as a combinatorial optimization task and receive MTS as inputs directly without sequence compressions. Then, to improve the combinatorial optimization efficiency and FS results in the high-dimensional case, a hybrid structure called enhanced evolutionary computation (EEC) is developed by combining with information theory-based feature priority scores, which play the role of semi-guidance in the iterative search. Test results on both the real-world and synthetic datasets validate the effectiveness of the developed EEC structure and show that the selected features by the proposed FS method are more beneficial in identifying the early patterns of network congestion events, thus contributing to efficient and accurate CEP for power systems.
A112: Main Program | B112: Other | C112: Score [0-5] | D112: Rationale | F112: Instructions: 1) Only modify colored cells. 2) Select the main program. 3) Evaluate all questions in the list. 4) Evaluate affinity score with integers 0, 1, 2, 3, 4, and 5 according to the scale below. 5) Provide a rationale for at least two low-, two medium-, and two high-classified questions. Prioritise questions where the classification was particularly difficult, uncertain, or ambiguous. Affinity Scale: Low ∎ 0: No conceptual overlap. The abstract addresses a completely different topic, phenomenon or research domain. There are no shared concepts, methods, or outcomes. Any superficial keyword match is coincidental. The abstract would not appear in a literature review for this question under any reasonable interpretation. ∎ 1: Marginal overlap. One or two terms or concepts are shared but the abstract investigates a fundamentally different question. The research domain may be adjacent but the objectives, topic, or outcomes are misaligned. Findings from this abstract could not be used to inform an answer to the question even partially. A reader would not cite this abstract as background for the question. Moderate ∎ 2: Contextual overlap. The abstract shares the general domain and studies a related concept or phenomenon, but targets a different outcome, phenomenon, or objective. The abstract provides useful background or framing but cannot directly answer the question. A reader might cite it to establish context but not as evidence. ∎ 3: Partial evidence. The abstract addresses the same research objective as the question but in a different area, context, or with a different methodological framework. Findings are relevant but require adaptation or extrapolation to apply to the question. A reader would cite this abstract as indirect or supporting evidence, not as a primary source. High ∎ 4: Direct relevance. The abstract addresses the same question, phenomenon, and outcome. Minor differences in methodology, setting, or scope exist but do not prevent the findings from being directly applicable. A reader would cite this abstract as substantive evidence for answering the question. ∎ 5: Near-perfect match. The abstract is a primary source for the question. It addresses the same research question, phenomenon, outcome, and methodology with only incidental differences. A reader would consider this abstract central to any literature review on the question.
A113: Question | B113: {=INDIRECT(B112)} -> #REF!
A136: Abstract_Index | B136: ='Abstracts List'!A7 -> 71
A137: Document Title | B137: ='Abstracts List'!B7 -> Electromechanical Transient Modeling of the Low-Frequency AC System With Modular Multilevel Matrix Converter Stations
A138: Abstract | B138: ='Abstracts List'!C7 -> This paper studies the electromechanical transient modeling of a low-frequency AC (LFAC) system with modular multilevel matrix converter (M3C) stations. Firstly, the mathematical model of the M3C and its equivalent circuits are established. Then, an iterative power flow calculation algorithm for AC systems integrated with the M3C-LFAC system is developed. The dynamic model of the M3C for electromechanical transient simulation is studied and implemented in PSS/E. Based on a test system consisting of two asynchronous AC systems with an embedded M3C-LFAC system, comparisons between the electromechanical transient simulation results from PSS/E and the electromagnetic transient simulation results from PSCAD are conducted. The results from PSS/E and PSCAD coincide with each other well, and the validity of the established electromechanical transient model is proved. Lastly, a stability study of a modified New England 39-bus system with an embedded M3C-LFAC system is executed, and the characteristics of the M3C-LFAC system are presented.
A139: Main Program | B139: Other | C139: Score [0-5] | D139: Rationale | F139: Instructions: 1) Only modify colored cells. 2) Select the main program. 3) Evaluate all questions in the list. 4) Evaluate affinity score with integers 0, 1, 2, 3, 4, and 5 according to the scale below. 5) Provide a rationale for at least two low-, two medium-, and two high-classified questions. Prioritise questions where the classification was particularly difficult, uncertain, or ambiguous. Affinity Scale: Low ∎ 0: No conceptual overlap. The abstract addresses a completely different topic, phenomenon or research domain. There are no shared concepts, methods, or outcomes. Any superficial keyword match is coincidental. The abstract would not appear in a literature review for this question under any reasonable interpretation. ∎ 1: Marginal overlap. One or two terms or concepts are shared but the abstract investigates a fundamentally different question. The research domain may be adjacent but the objectives, topic, or outcomes are misaligned. Findings from this abstract could not be used to inform an answer to the question even partially. A reader would not cite this abstract as background for the question. Moderate ∎ 2: Contextual overlap. The abstract shares the general domain and studies a related concept or phenomenon, but targets a different outcome, phenomenon, or objective. The abstract provides useful background or framing but cannot directly answer the question. A reader might cite it to establish context but not as evidence. ∎ 3: Partial evidence. The abstract addresses the same research objective as the question but in a different area, context, or with a different methodological framework. Findings are relevant but require adaptation or extrapolation to apply to the question. A reader would cite this abstract as indirect or supporting evidence, not as a primary source. High ∎ 4: Direct relevance. The abstract addresses the same question, phenomenon, and outcome. Minor differences in methodology, setting, or scope exist but do not prevent the findings from being directly applicable. A reader would cite this abstract as substantive evidence for answering the question. ∎ 5: Near-perfect match. The abstract is a primary source for the question. It addresses the same research question, phenomenon, outcome, and methodology with only incidental differences. A reader would consider this abstract central to any literature review on the question.
A140: Question | B140: {=INDIRECT(B139)} -> #REF!
A163: Abstract_Index | B163: ='Abstracts List'!A8 -> 146
A164: Document Title | B164: ='Abstracts List'!B8 -> Automatic Generation of Topology Diagrams for Strongly-Meshed Power Transmission Systems
A165: Abstract | B165: ='Abstracts List'!C8 -> Topology diagrams are widely seen in power system applications, but their automatic generation is often easier said than done. When facing power transmission systems with strongly-meshed structures, existing approaches can hardly produce topology diagrams catering to the aesthetics of readers. This paper proposes an integrated framework for generating aesthetically-pleasing topology diagrams for power transmission systems. Input with a rough layout, the framework first conducts visibility region analysis to reduce line crossings and then solves a mixed-integer linear programming problem to optimize the arrangement of nodes. Given that the complexity of both modules is pretty high, simplification heuristics are also proposed to enhance the efficiency of the framework. Case studies on several power transmission systems containing up to 2,046 nodes demonstrate the capability of the proposed framework in generating topology diagrams conforming to aesthetic criteria in the power system community. Compared with the widespread force-directed algorithm, the proposed framework can preserve the relative positions of nodes in the original layout to a great extent, which significantly contributes to the identification of electrical elements on the diagrams. Meanwhile, the time consumption is acceptable for practical applications.
A166: Main Program | B166: Other | C166: Score [0-5] | D166: Rationale | F166: Instructions: 1) Only modify colored cells. 2) Select the main program. 3) Evaluate all questions in the list. 4) Evaluate affinity score with integers 0, 1, 2, 3, 4, and 5 according to the scale below. 5) Provide a rationale for at least two low-, two medium-, and two high-classified questions. Prioritise questions where the classification was particularly difficult, uncertain, or ambiguous. Affinity Scale: Low ∎ 0: No conceptual overlap. The abstract addresses a completely different topic, phenomenon or research domain. There are no shared concepts, methods, or outcomes. Any superficial keyword match is coincidental. The abstract would not appear in a literature review for this question under any reasonable interpretation. ∎ 1: Marginal overlap. One or two terms or concepts are shared but the abstract investigates a fundamentally different question. The research domain may be adjacent but the objectives, topic, or outcomes are misaligned. Findings from this abstract could not be used to inform an answer to the question even partially. A reader would not cite this abstract as background for the question. Moderate ∎ 2: Contextual overlap. The abstract shares the general domain and studies a related concept or phenomenon, but targets a different outcome, phenomenon, or objective. The abstract provides useful background or framing but cannot directly answer the question. A reader might cite it to establish context but not as evidence. ∎ 3: Partial evidence. The abstract addresses the same research objective as the question but in a different area, context, or with a different methodological framework. Findings are relevant but require adaptation or extrapolation to apply to the question. A reader would cite this abstract as indirect or supporting evidence, not as a primary source. High ∎ 4: Direct relevance. The abstract addresses the same question, phenomenon, and outcome. Minor differences in methodology, setting, or scope exist but do not prevent the findings from being directly applicable. A reader would cite this abstract as substantive evidence for answering the question. ∎ 5: Near-perfect match. The abstract is a primary source for the question. It addresses the same research question, phenomenon, outcome, and methodology with only incidental differences. A reader would consider this abstract central to any literature review on the question.
A167: Question | B167: {=INDIRECT(B166)} -> #REF!
A190: Abstract_Index | B190: ='Abstracts List'!A9 -> 65
A191: Document Title | B191: ='Abstracts List'!B9 -> Cooperative Hierarchical Control of Isolated Microgrids Considering Energy Storage System Aggregation
A192: Abstract | B192: ='Abstracts List'!C9 -> The integration of numerous energy storage systems (ESSs) improves the reliable and economic operation of microgrids but also enlarges the burden of control and communication systems. This article proposes a cooperative hierarchical control for isolated microgrids with ESSs, which fully frees from the centralized paradigm and is therefore superior in flexibility and scalability. Firstly, the ESS cooperative control based on the distributed frequency controller is introduced for the state of charge (SoC) balance and the frequency regulation. Then, the ESS aggregation is considered. The aggregated ESS model is established and the real-time model parameters are derived by proposed distributed state observers. Finally, energy management is employed to allocate the output power between generators and the aggregated ESS. A detailed theoretical analysis of the dynamic and steady-state performance of proposed controllers and observers is provided. Simulations on the IEEE 33-bus and the 69-bus system verify the effectiveness of proposed methods.
A193: Main Program | B193: Other | C193: Score [0-5] | D193: Rationale | F193: Instructions: 1) Only modify colored cells. 2) Select the main program. 3) Evaluate all questions in the list. 4) Evaluate affinity score with integers 0, 1, 2, 3, 4, and 5 according to the scale below. 5) Provide a rationale for at least two low-, two medium-, and two high-classified questions. Prioritise questions where the classification was particularly difficult, uncertain, or ambiguous. Affinity Scale: Low ∎ 0: No conceptual overlap. The abstract addresses a completely different topic, phenomenon or research domain. There are no shared concepts, methods, or outcomes. Any superficial keyword match is coincidental. The abstract would not appear in a literature review for this question under any reasonable interpretation. ∎ 1: Marginal overlap. One or two terms or concepts are shared but the abstract investigates a fundamentally different question. The research domain may be adjacent but the objectives, topic, or outcomes are misaligned. Findings from this abstract could not be used to inform an answer to the question even partially. A reader would not cite this abstract as background for the question. Moderate ∎ 2: Contextual overlap. The abstract shares the general domain and studies a related concept or phenomenon, but targets a different outcome, phenomenon, or objective. The abstract provides useful background or framing but cannot directly answer the question. A reader might cite it to establish context but not as evidence. ∎ 3: Partial evidence. The abstract addresses the same research objective as the question but in a different area, context, or with a different methodological framework. Findings are relevant but require adaptation or extrapolation to apply to the question. A reader would cite this abstract as indirect or supporting evidence, not as a primary source. High ∎ 4: Direct relevance. The abstract addresses the same question, phenomenon, and outcome. Minor differences in methodology, setting, or scope exist but do not prevent the findings from being directly applicable. A reader would cite this abstract as substantive evidence for answering the question. ∎ 5: Near-perfect match. The abstract is a primary source for the question. It addresses the same research question, phenomenon, outcome, and methodology with only incidental differences. A reader would consider this abstract central to any literature review on the question.
A194: Question | B194: {=INDIRECT(B193)} -> #REF!
A217: Abstract_Index | B217: ='Abstracts List'!A10 -> 281
A218: Document Title | B218: ='Abstracts List'!B10 -> Minimum Energy Demands of Energy Storages for Fast Frequency Response: Formulation, Solution, and Implementation
A219: Abstract | B219: ='Abstracts List'!C10 -> Energy storage (ES) is a kind of promising but costly fast-frequency-response (FFR) resource in low-inertia power systems. This article addresses the minimum demand of a power system for energy capacities of ES to providing sufficient frequency support, including the formulation, the optimal solution, and its practical implementation. First, the minimum energy control problem of ESs for providing FFR with transient frequency constraints is formulated and then converted into an optimal frequency trajectory planning counterpart. This transformation makes the transient frequency constraint tractable and allows to identify the optimal frequency trajectory that minimizes energy demand for ESs, which leads to an analytical expression of the system minimum demand for ESs energy capacities to ensure frequency security. Moreover, by unfolding the optimal frequency trajectory, the optimal control strategy of ESs is derived explicitly for the first time. The theoretical result directs to a practical controller implementation, which is referred to as the decentralized optimal energy frequency control (DOEFC). Finally, simulations on the modified IEEE 39-bus system verify our results and demonstrate the superiority of the DOEFC in reducing the energy capacity demand of ESs, defending successive disturbances, and hedging against parameter errors.
A220: Main Program | B220: Other | C220: Score [0-5] | D220: Rationale | F220: Instructions: 1) Only modify colored cells. 2) Select the main program. 3) Evaluate all questions in the list. 4) Evaluate affinity score with integers 0, 1, 2, 3, 4, and 5 according to the scale below. 5) Provide a rationale for at least two low-, two medium-, and two high-classified questions. Prioritise questions where the classification was particularly difficult, uncertain, or ambiguous. Affinity Scale: Low ∎ 0: No conceptual overlap. The abstract addresses a completely different topic, phenomenon or research domain. There are no shared concepts, methods, or outcomes. Any superficial keyword match is coincidental. The abstract would not appear in a literature review for this question under any reasonable interpretation. ∎ 1: Marginal overlap. One or two terms or concepts are shared but the abstract investigates a fundamentally different question. The research domain may be adjacent but the objectives, topic, or outcomes are misaligned. Findings from this abstract could not be used to inform an answer to the question even partially. A reader would not cite this abstract as background for the question. Moderate ∎ 2: Contextual overlap. The abstract shares the general domain and studies a related concept or phenomenon, but targets a different outcome, phenomenon, or objective. The abstract provides useful background or framing but cannot directly answer the question. A reader might cite it to establish context but not as evidence. ∎ 3: Partial evidence. The abstract addresses the same research objective as the question but in a different area, context, or with a different methodological framework. Findings are relevant but require adaptation or extrapolation to apply to the question. A reader would cite this abstract as indirect or supporting evidence, not as a primary source. High ∎ 4: Direct relevance. The abstract addresses the same question, phenomenon, and outcome. Minor differences in methodology, setting, or scope exist but do not prevent the findings from being directly applicable. A reader would cite this abstract as substantive evidence for answering the question. ∎ 5: Near-perfect match. The abstract is a primary source for the question. It addresses the same research question, phenomenon, outcome, and methodology with only incidental differences. A reader would consider this abstract central to any literature review on the question.
A221: Question | B221: {=INDIRECT(B220)} -> #REF!
A244: Abstract_Index | B244: ='Abstracts List'!A13 -> 241
A245: Document Title | B245: ='Abstracts List'!B13 -> Adaptive Weighted Combination Approach for Wind Power Forecast Based on Deep Deterministic Policy Gradient Method
A246: Abstract | B246: ='Abstracts List'!C13 -> Accurate wind power forecast (WPF) is critical for ensuring secure and economic operation of a power system, and combination forecasting approaches for WPF have been proved effective on attaining accurate forecasting results. However, the weights in a combination forecasting model are usually predetermined based on the global performance on the training set, limiting the adaptability of the model to different scenarios. To further enhance the accuracy and effectiveness of the combination forecasting approaches, this article proposes an adaptive weighted combination forecasting approach based on the deep deterministic policy gradient (DDPG) so as to consider the local behavior accompanied by the change of external environment. Three sub-models are first selected considering the equal-likelihood and dispersion indices to construct a combination model. Then, the DDPG agent is trained to act as a weight generator by interacting with the environment and to maximize the reward. Thus, the DDPG agent can perceive the environmental changes online and dynamically weight the sub-models to attain accurate forecasting results. Case studies demonstrate that the forecasting accuracy of the proposed approach is better than that of all sub-models and several benchmark combination forecasting approaches.
A247: Main Program | B247: Other | C247: Score [0-5] | D247: Rationale | F247: Instructions: 1) Only modify colored cells. 2) Select the main program. 3) Evaluate all questions in the list. 4) Evaluate affinity score with integers 0, 1, 2, 3, 4, and 5 according to the scale below. 5) Provide a rationale for at least two low-, two medium-, and two high-classified questions. Prioritise questions where the classification was particularly difficult, uncertain, or ambiguous. Affinity Scale: Low ∎ 0: No conceptual overlap. The abstract addresses a completely different topic, phenomenon or research domain. There are no shared concepts, methods, or outcomes. Any superficial keyword match is coincidental. The abstract would not appear in a literature review for this question under any reasonable interpretation. ∎ 1: Marginal overlap. One or two terms or concepts are shared but the abstract investigates a fundamentally different question. The research domain may be adjacent but the objectives, topic, or outcomes are misaligned. Findings from this abstract could not be used to inform an answer to the question even partially. A reader would not cite this abstract as background for the question. Moderate ∎ 2: Contextual overlap. The abstract shares the general domain and studies a related concept or phenomenon, but targets a different outcome, phenomenon, or objective. The abstract provides useful background or framing but cannot directly answer the question. A reader might cite it to establish context but not as evidence. ∎ 3: Partial evidence. The abstract addresses the same research objective as the question but in a different area, context, or with a different methodological framework. Findings are relevant but require adaptation or extrapolation to apply to the question. A reader would cite this abstract as indirect or supporting evidence, not as a primary source. High ∎ 4: Direct relevance. The abstract addresses the same question, phenomenon, and outcome. Minor differences in methodology, setting, or scope exist but do not prevent the findings from being directly applicable. A reader would cite this abstract as substantive evidence for answering the question. ∎ 5: Near-perfect match. The abstract is a primary source for the question. It addresses the same research question, phenomenon, outcome, and methodology with only incidental differences. A reader would consider this abstract central to any literature review on the question.
A248: Question | B248: {=INDIRECT(B247)} -> #REF!
A271: Abstract_Index | B271: ='Abstracts List'!A14 -> 94
A272: Document Title | B272: ='Abstracts List'!B14 -> An AC-Feasible Linear Model in Distribution Networks With Energy Storage
A273: Abstract | B273: ='Abstracts List'!C14 -> With the increasing deployment of distributed energy resources (DERs), dispatching DERs subject to operational constraints in distribution networks draws much attention. One challenge is the non-convexities in 1) system-wide AC power flow constraints and 2) the individual complementarity constraint of energy storage. To resolve this challenge, this paper studies an AC-feasible linear model in distribution networks with energy storage, including its formulation, analysis, and applications. First, an AC-feasible linear model is formulated as a set of linear constraints on controllable DERs and uncontrollable power demand by 1) converting the non-convex system-wide constraints into linear constraints based on the Brouwer's fixed-point theorem and the second-order Taylor expansion, and 2) replacing the non-convex individual complementarity constraint of energy storage with one properly designed linear constraint. Furthermore, to analyze the power demand level at which the proposed linear model can provide a solution, this paper proposes an examination-based projection method under the Monte Carlo framework to handle projections of thousands of dimensions from linear constraints over time periods. Finally, the potential applications of our AC-feasible linear model are discussed. Numerical experiments are conducted in the IEEE 33-bus and 136-bus test systems to demonstrate the effectiveness of the proposed methods.
A274: Main Program | B274: Other | C274: Score [0-5] | D274: Rationale | F274: Instructions: 1) Only modify colored cells. 2) Select the main program. 3) Evaluate all questions in the list. 4) Evaluate affinity score with integers 0, 1, 2, 3, 4, and 5 according to the scale below. 5) Provide a rationale for at least two low-, two medium-, and two high-classified questions. Prioritise questions where the classification was particularly difficult, uncertain, or ambiguous. Affinity Scale: Low ∎ 0: No conceptual overlap. The abstract addresses a completely different topic, phenomenon or research domain. There are no shared concepts, methods, or outcomes. Any superficial keyword match is coincidental. The abstract would not appear in a literature review for this question under any reasonable interpretation. ∎ 1: Marginal overlap. One or two terms or concepts are shared but the abstract investigates a fundamentally different question. The research domain may be adjacent but the objectives, topic, or outcomes are misaligned. Findings from this abstract could not be used to inform an answer to the question even partially. A reader would not cite this abstract as background for the question. Moderate ∎ 2: Contextual overlap. The abstract shares the general domain and studies a related concept or phenomenon, but targets a different outcome, phenomenon, or objective. The abstract provides useful background or framing but cannot directly answer the question. A reader might cite it to establish context but not as evidence. ∎ 3: Partial evidence. The abstract addresses the same research objective as the question but in a different area, context, or with a different methodological framework. Findings are relevant but require adaptation or extrapolation to apply to the question. A reader would cite this abstract as indirect or supporting evidence, not as a primary source. High ∎ 4: Direct relevance. The abstract addresses the same question, phenomenon, and outcome. Minor differences in methodology, setting, or scope exist but do not prevent the findings from being directly applicable. A reader would cite this abstract as substantive evidence for answering the question. ∎ 5: Near-perfect match. The abstract is a primary source for the question. It addresses the same research question, phenomenon, outcome, and methodology with only incidental differences. A reader would consider this abstract central to any literature review on the question.
A275: Question | B275: {=INDIRECT(B274)} -> #REF!
A298: Abstract_Index | B298: ='Abstracts List'!A15 -> 44
A299: Document Title | B299: ='Abstracts List'!B15 -> Hierarchical Control Strategy for Effective Virtual Frequency Responses of Multiple WPPs
A300: Abstract | B300: ='Abstracts List'!C15 -> When renewable energy-based generations are increasing, they are subject to cause frequency stability problems in a power system. To solve this problem, various virtual inertial control methods (VICMs) have been recently developed. However, they all have dealt not with the steady-state frequency stability, but only with dynamic frequency stability issues. In particular, the wind power plants (WPPs) operated by these VICMs can only provide a similar inertial response (IR) to that by conventional synchronous generators without providing the primary frequency response (PFR). This results in lowering the settling frequency (SF) below the maximum steady-state frequency deviation (MSSD) band. This paper proposes the new hierarchical control strategy for the WPPs, which are operated by three virtual frequency response control methods (VFRCMs) to provide both IR and PFR. Firstly, the VFRCM-1 provides virtual IR. Next, the VFRCM-2 increases the output power from the WPPs to prevent the frequency drop, which can occur after the frequency nadir is arrested. Finally, the VFRCM-3 makes the WPPs possible to raise the SF above the MSSD band by providing the virtual PFR. The effectiveness of proposed hierarchical control strategy is verified by several case studies on the IEEE 39-bus test system with the high penetration of renewables.
A301: Main Program | B301: Other | C301: Score [0-5] | D301: Rationale | F301: Instructions: 1) Only modify colored cells. 2) Select the main program. 3) Evaluate all questions in the list. 4) Evaluate affinity score with integers 0, 1, 2, 3, 4, and 5 according to the scale below. 5) Provide a rationale for at least two low-, two medium-, and two high-classified questions. Prioritise questions where the classification was particularly difficult, uncertain, or ambiguous. Affinity Scale: Low ∎ 0: No conceptual overlap. The abstract addresses a completely different topic, phenomenon or research domain. There are no shared concepts, methods, or outcomes. Any superficial keyword match is coincidental. The abstract would not appear in a literature review for this question under any reasonable interpretation. ∎ 1: Marginal overlap. One or two terms or concepts are shared but the abstract investigates a fundamentally different question. The research domain may be adjacent but the objectives, topic, or outcomes are misaligned. Findings from this abstract could not be used to inform an answer to the question even partially. A reader would not cite this abstract as background for the question. Moderate ∎ 2: Contextual overlap. The abstract shares the general domain and studies a related concept or phenomenon, but targets a different outcome, phenomenon, or objective. The abstract provides useful background or framing but cannot directly answer the question. A reader might cite it to establish context but not as evidence. ∎ 3: Partial evidence. The abstract addresses the same research objective as the question but in a different area, context, or with a different methodological framework. Findings are relevant but require adaptation or extrapolation to apply to the question. A reader would cite this abstract as indirect or supporting evidence, not as a primary source. High ∎ 4: Direct relevance. The abstract addresses the same question, phenomenon, and outcome. Minor differences in methodology, setting, or scope exist but do not prevent the findings from being directly applicable. A reader would cite this abstract as substantive evidence for answering the question. ∎ 5: Near-perfect match. The abstract is a primary source for the question. It addresses the same research question, phenomenon, outcome, and methodology with only incidental differences. A reader would consider this abstract central to any literature review on the question.
A302: Question | B302: {=INDIRECT(B301)} -> #REF!
A325: Abstract_Index | B325: ='Abstracts List'!A16 -> 185
A326: Document Title | B326: ='Abstracts List'!B16 -> Practical Methods of Defective Input Feature Correction to Enable Machine Learning in Power Systems
A327: Abstract | B327: ='Abstracts List'!C16 -> In this research work, three practical correction methods are proposed to mitigate the impact of defective input features in power system data measurement for machine learning (ML) applications. A well-trained ML tool may become ineffective due to defective input features, which may originate from measurement issues, such as monitor malfunction, cyberattack, communication failure, or others. It is crucial to correct defective input features to enable ML tools with desirable performances. This letter first introduces the mechanism of three correction methods, i.e., statistical-value-based method, minimal-error-based method, and DNN-based adaptive method. Then, the methods are validated via a deep neural network (DNN) case for power system stability enhancement. Validation results demonstrate that the adaptive method achieves the best performance, enabling the well-trained ML tool with a similar accuracy level to the case of no data defects. Although actual measurements may have various data issues challenging ML applications in power systems, the proposed methods show promise for addressing these challenges.
A328: Main Program | B328: Other | C328: Score [0-5] | D328: Rationale | F328: Instructions: 1) Only modify colored cells. 2) Select the main program. 3) Evaluate all questions in the list. 4) Evaluate affinity score with integers 0, 1, 2, 3, 4, and 5 according to the scale below. 5) Provide a rationale for at least two low-, two medium-, and two high-classified questions. Prioritise questions where the classification was particularly difficult, uncertain, or ambiguous. Affinity Scale: Low ∎ 0: No conceptual overlap. The abstract addresses a completely different topic, phenomenon or research domain. There are no shared concepts, methods, or outcomes. Any superficial keyword match is coincidental. The abstract would not appear in a literature review for this question under any reasonable interpretation. ∎ 1: Marginal overlap. One or two terms or concepts are shared but the abstract investigates a fundamentally different question. The research domain may be adjacent but the objectives, topic, or outcomes are misaligned. Findings from this abstract could not be used to inform an answer to the question even partially. A reader would not cite this abstract as background for the question. Moderate ∎ 2: Contextual overlap. The abstract shares the general domain and studies a related concept or phenomenon, but targets a different outcome, phenomenon, or objective. The abstract provides useful background or framing but cannot directly answer the question. A reader might cite it to establish context but not as evidence. ∎ 3: Partial evidence. The abstract addresses the same research objective as the question but in a different area, context, or with a different methodological framework. Findings are relevant but require adaptation or extrapolation to apply to the question. A reader would cite this abstract as indirect or supporting evidence, not as a primary source. High ∎ 4: Direct relevance. The abstract addresses the same question, phenomenon, and outcome. Minor differences in methodology, setting, or scope exist but do not prevent the findings from being directly applicable. A reader would cite this abstract as substantive evidence for answering the question. ∎ 5: Near-perfect match. The abstract is a primary source for the question. It addresses the same research question, phenomenon, outcome, and methodology with only incidental differences. A reader would consider this abstract central to any literature review on the question.
A329: Question | B329: {=INDIRECT(B328)} -> #REF!
A352: Abstract_Index | B352: ='Abstracts List'!A17 -> 174
A353: Document Title | B353: ='Abstracts List'!B17 -> Chance-Constrained Optimization Based PV Hosting Capacity Calculation Using General Polynomial Chaos
A354: Abstract | B354: ='Abstracts List'!C17 -> Increased penetration of renewable resources and new loads have increased the uncertainty levels in low voltage distribution systems (LVDS). This requires considering LVDS planning, such as computing photovoltaics (PV) hosting capacity (HC), as a stochastic problem. Traditionally, PV HC is computed using the iterative Monte Carlo method, which requires solving the power flow equations thousands of times. This paper proposes a chance-constrained optimization-based hosting capacity calculation technique, which eliminates the necessity of repetitive solving of power flow equations. The intrusive general polynomial chaos expansion is used to translate the input uncertainties defined by their probability density function to the hosting capacity of the network without the necessity of sampling, linearizing the power flow equations, or applying any relaxations. Chance constraints are applied for nodal voltages and thermal overload as per the norms, where the system can be congested for a certain time without affecting the power quality. Numerical illustrations show the computational time to compute the stochastic PV hosting capacity of a real large scale LVDS, and for the majority of the feeders, it falls within 100 sec. Furthermore, the estimated PV HC using this stochastic optimal power flow was, on average, 20% higher than its deterministic counterpart.
A355: Main Program | B355: Other | C355: Score [0-5] | D355: Rationale | F355: Instructions: 1) Only modify colored cells. 2) Select the main program. 3) Evaluate all questions in the list. 4) Evaluate affinity score with integers 0, 1, 2, 3, 4, and 5 according to the scale below. 5) Provide a rationale for at least two low-, two medium-, and two high-classified questions. Prioritise questions where the classification was particularly difficult, uncertain, or ambiguous. Affinity Scale: Low ∎ 0: No conceptual overlap. The abstract addresses a completely different topic, phenomenon or research domain. There are no shared concepts, methods, or outcomes. Any superficial keyword match is coincidental. The abstract would not appear in a literature review for this question under any reasonable interpretation. ∎ 1: Marginal overlap. One or two terms or concepts are shared but the abstract investigates a fundamentally different question. The research domain may be adjacent but the objectives, topic, or outcomes are misaligned. Findings from this abstract could not be used to inform an answer to the question even partially. A reader would not cite this abstract as background for the question. Moderate ∎ 2: Contextual overlap. The abstract shares the general domain and studies a related concept or phenomenon, but targets a different outcome, phenomenon, or objective. The abstract provides useful background or framing but cannot directly answer the question. A reader might cite it to establish context but not as evidence. ∎ 3: Partial evidence. The abstract addresses the same research objective as the question but in a different area, context, or with a different methodological framework. Findings are relevant but require adaptation or extrapolation to apply to the question. A reader would cite this abstract as indirect or supporting evidence, not as a primary source. High ∎ 4: Direct relevance. The abstract addresses the same question, phenomenon, and outcome. Minor differences in methodology, setting, or scope exist but do not prevent the findings from being directly applicable. A reader would cite this abstract as substantive evidence for answering the question. ∎ 5: Near-perfect match. The abstract is a primary source for the question. It addresses the same research question, phenomenon, outcome, and methodology with only incidental differences. A reader would consider this abstract central to any literature review on the question.
A356: Question | B356: {=INDIRECT(B355)} -> #REF!
A379: Abstract_Index | B379: ='Abstracts List'!A18 -> 194
A380: Document Title | B380: ='Abstracts List'!B18 -> Analysis of Long-Term Indicators in the British Balancing Market
A381: Abstract | B381: ='Abstracts List'!C18 -> Proactive participation of uncertain renewable generation in the day-ahead (DA) wholesale market effectively reduces the system marginal price and carbon emissions, whilst significantly increasing the volumes of real-time balancing mechanism prices to ensure system security and stability. To solve the conflicting interests over the two timescales, this article: 1) proposes a novel hierarchical optimization model to align with the actual operation paradigms of the hierarchical market, whereby the capacity allocation matrix is adopted to coordinate the DA and balancing markets; 2) mathematically formulates and quantitatively analyses the long-term driving factors of balancing actions, enabling system operators (SOs) to design efficient and well-functioning market structures to meet economic and environmental targets; 3) empowers renewable generating units and flexible loads to participate in the balancing market (BM) as Ã¢â‚¬ËœactiveÃ¢â‚¬â„¢ actors and enforces the non-discriminatory provision of balancing services. The performance of the proposed model is validated on a modified IEEE 39-bus power system and a reduced GB network. Results reveal that with effective resource allocation in different timescales of the hierarchical market, the drop speed of balancing costs soars while the intermittent generation climbs. The proposed methodology enables SOs to make the most of all resources available in the market and balance the system flexibly and economically. It thus safeguards the climate mitigation pathways against the risks of substantially higher balancing costs.
A382: Main Program | B382: Other | C382: Score [0-5] | D382: Rationale | F382: Instructions: 1) Only modify colored cells. 2) Select the main program. 3) Evaluate all questions in the list. 4) Evaluate affinity score with integers 0, 1, 2, 3, 4, and 5 according to the scale below. 5) Provide a rationale for at least two low-, two medium-, and two high-classified questions. Prioritise questions where the classification was particularly difficult, uncertain, or ambiguous. Affinity Scale: Low ∎ 0: No conceptual overlap. The abstract addresses a completely different topic, phenomenon or research domain. There are no shared concepts, methods, or outcomes. Any superficial keyword match is coincidental. The abstract would not appear in a literature review for this question under any reasonable interpretation. ∎ 1: Marginal overlap. One or two terms or concepts are shared but the abstract investigates a fundamentally different question. The research domain may be adjacent but the objectives, topic, or outcomes are misaligned. Findings from this abstract could not be used to inform an answer to the question even partially. A reader would not cite this abstract as background for the question. Moderate ∎ 2: Contextual overlap. The abstract shares the general domain and studies a related concept or phenomenon, but targets a different outcome, phenomenon, or objective. The abstract provides useful background or framing but cannot directly answer the question. A reader might cite it to establish context but not as evidence. ∎ 3: Partial evidence. The abstract addresses the same research objective as the question but in a different area, context, or with a different methodological framework. Findings are relevant but require adaptation or extrapolation to apply to the question. A reader would cite this abstract as indirect or supporting evidence, not as a primary source. High ∎ 4: Direct relevance. The abstract addresses the same question, phenomenon, and outcome. Minor differences in methodology, setting, or scope exist but do not prevent the findings from being directly applicable. A reader would cite this abstract as substantive evidence for answering the question. ∎ 5: Near-perfect match. The abstract is a primary source for the question. It addresses the same research question, phenomenon, outcome, and methodology with only incidental differences. A reader would consider this abstract central to any literature review on the question.
A383: Question | B383: {=INDIRECT(B382)} -> #REF!
A406: Abstract_Index | B406: ='Abstracts List'!A20 -> 212
A407: Document Title | B407: ='Abstracts List'!B20 -> Comparative Analysis of the Power Output Capabilities of Grid-Following and Grid-Forming Inverters Considering Static, Dynamic, and Thermal Limitations
A408: Abstract | B408: ='Abstracts List'!C20 -> This article investigates the maximum transferable power (MTP) of inverter-based resources (IBRs) and provides the output capability curves (OCCs) of grid-tied grid-following inverters (GFLIs) and grid-forming inverters (GFMIs). To this end, in the first part of the article, mathematical equations for GFLI static, thermal, and phase-locked loop (PLL)-induced power transfer limits are derived in terms of the grid short-circuit ratio (SCR) and its X/R ratio. Then, considering other operational limitations, such as the IBR AC- and DC-side voltage limits, the OCC of the GFLI is obtained. Additionally, the impact of the reactive current and the reactive control mode on the OCC is further studied, and accordingly, an auxiliary control loop is proposed to maximize the GFLI MTP. In the second part of the article, a similar approach is employed to derive mathematical equations for GFMI static and thermal limits, and accordingly, the OCC of a GFMI is obtained. The effects of the variation of the voltage set-point of the GFMI on its OCC are then studied, and the superiority of GFMIs compared to GFLIs is shown in terms of the MTP capability. Eventually, several simulation and experimental cases are conducted to validate the obtained equations and OCCs for both grid-following and grid-forming control modes.
A409: Main Program | B409: Other | C409: Score [0-5] | D409: Rationale | F409: Instructions: 1) Only modify colored cells. 2) Select the main program. 3) Evaluate all questions in the list. 4) Evaluate affinity score with integers 0, 1, 2, 3, 4, and 5 according to the scale below. 5) Provide a rationale for at least two low-, two medium-, and two high-classified questions. Prioritise questions where the classification was particularly difficult, uncertain, or ambiguous. Affinity Scale: Low ∎ 0: No conceptual overlap. The abstract addresses a completely different topic, phenomenon or research domain. There are no shared concepts, methods, or outcomes. Any superficial keyword match is coincidental. The abstract would not appear in a literature review for this question under any reasonable interpretation. ∎ 1: Marginal overlap. One or two terms or concepts are shared but the abstract investigates a fundamentally different question. The research domain may be adjacent but the objectives, topic, or outcomes are misaligned. Findings from this abstract could not be used to inform an answer to the question even partially. A reader would not cite this abstract as background for the question. Moderate ∎ 2: Contextual overlap. The abstract shares the general domain and studies a related concept or phenomenon, but targets a different outcome, phenomenon, or objective. The abstract provides useful background or framing but cannot directly answer the question. A reader might cite it to establish context but not as evidence. ∎ 3: Partial evidence. The abstract addresses the same research objective as the question but in a different area, context, or with a different methodological framework. Findings are relevant but require adaptation or extrapolation to apply to the question. A reader would cite this abstract as indirect or supporting evidence, not as a primary source. High ∎ 4: Direct relevance. The abstract addresses the same question, phenomenon, and outcome. Minor differences in methodology, setting, or scope exist but do not prevent the findings from being directly applicable. A reader would cite this abstract as substantive evidence for answering the question. ∎ 5: Near-perfect match. The abstract is a primary source for the question. It addresses the same research question, phenomenon, outcome, and methodology with only incidental differences. A reader would consider this abstract central to any literature review on the question.
A410: Question | B410: {=INDIRECT(B409)} -> #REF!
A433: Abstract_Index | B433: ='Abstracts List'!A21 -> 15
A434: Document Title | B434: ='Abstracts List'!B21 -> Look-Ahead Rolling Economic Dispatch Approach for Wind-Thermal-Bundled Power System Considering Dynamic Ramping and Flexible Load Transfer Strategy
A435: Abstract | B435: ='Abstracts List'!C21 -> With a wind-thermal-bundled power system (WTBPS) under high wind penetration levels, the sharp power fluctuations of tie-lines for interconnected grids trigger a significant challenge of security-constrained power system operation. Smoothing power fluctuations with economic dispatch is widely concerned against this challenge. In this paper, an appropriate look-ahead economic dispatch framework for WTBPS considering the variable ramp rate of retrofitted coal-fired units and the flexible load transfer strategy (LTS) in high voltage distribution networks (HVDNs) is proposed. To cope with this issue, i) we derive a new family of tightened ramping constraints of retrofitted coal-fired units in the linear and second-order conic (SOC) forms, respectively. ii) Using graph characterization of typical HVDNs, the simplified voltage-constrained LTS via topological structures can be developed. This proposed look-ahead economic dispatch model is cast as a mixed-integer second-order cone programming (MISOCP) problem, which can be reformulated by Multi-cut Generalized Benders Decomposition (MGBD). This MGBD enables multiple sub-problems can be solved in parallel and accelerates the solving process. Finally, simulation results of a large-scale practical system validate the computational accuracy and efficiency of the proposed approach.
A436: Main Program | B436: Other | C436: Score [0-5] | D436: Rationale | F436: Instructions: 1) Only modify colored cells. 2) Select the main program. 3) Evaluate all questions in the list. 4) Evaluate affinity score with integers 0, 1, 2, 3, 4, and 5 according to the scale below. 5) Provide a rationale for at least two low-, two medium-, and two high-classified questions. Prioritise questions where the classification was particularly difficult, uncertain, or ambiguous. Affinity Scale: Low ∎ 0: No conceptual overlap. The abstract addresses a completely different topic, phenomenon or research domain. There are no shared concepts, methods, or outcomes. Any superficial keyword match is coincidental. The abstract would not appear in a literature review for this question under any reasonable interpretation. ∎ 1: Marginal overlap. One or two terms or concepts are shared but the abstract investigates a fundamentally different question. The research domain may be adjacent but the objectives, topic, or outcomes are misaligned. Findings from this abstract could not be used to inform an answer to the question even partially. A reader would not cite this abstract as background for the question. Moderate ∎ 2: Contextual overlap. The abstract shares the general domain and studies a related concept or phenomenon, but targets a different outcome, phenomenon, or objective. The abstract provides useful background or framing but cannot directly answer the question. A reader might cite it to establish context but not as evidence. ∎ 3: Partial evidence. The abstract addresses the same research objective as the question but in a different area, context, or with a different methodological framework. Findings are relevant but require adaptation or extrapolation to apply to the question. A reader would cite this abstract as indirect or supporting evidence, not as a primary source. High ∎ 4: Direct relevance. The abstract addresses the same question, phenomenon, and outcome. Minor differences in methodology, setting, or scope exist but do not prevent the findings from being directly applicable. A reader would cite this abstract as substantive evidence for answering the question. ∎ 5: Near-perfect match. The abstract is a primary source for the question. It addresses the same research question, phenomenon, outcome, and methodology with only incidental differences. A reader would consider this abstract central to any literature review on the question.
A437: Question | B437: {=INDIRECT(B436)} -> #REF!
A460: Abstract_Index | B460: ='Abstracts List'!A22 -> 231
A461: Document Title | B461: ='Abstracts List'!B22 -> Centralized Distributionally Robust Chance-Constrained Dispatch of Integrated Transmission-Distribution Systems
...

Sheet Question context
A1: Group | B1: Subgrouping | C1: RA2025 | D1: Questions - long | E1: 1 | F1: 103 | G1: 115 | H1: 81 | I1: 134 | J1: 71 | K1: 146 | L1: 65 | M1: 281 | N1: 241 | O1: 94 | P1: 44 | Q1: 185 | R1: 174 | S1: 194 | T1: 212 | U1: 15 | V1: 231 | W1: 228 | X1: 45 | Y1: 280
A2: IBR | B2: I1 - Power system evolution with high IBR shares | C2: 1 | D2: What is the future of active power balance as the synchronous generation fraction reduces? For example, might tightened or loosened frequency (or similar proxy for active power balance) limits lead to a more reliable, secure, lower-cost IBR-based power system?
C3: 2 | D3: How will protection systems need to change to accommodate high penetrations of IBRs, and what possible actions might an inverter take during a fault that would help fault detection and location? | F3: 3
C4: 3 | D4: How could the IBR control paradigm change from replicating synchronous machines to exploiting wider IBR flexibility without introducing integration challenges during the transition? | P4: 1
B5: I2 - IBR design standards and capabilities | C5: 4 | D5: What are the appropriate inverter capabilities and, consequently, control design methods for operation in grids with high percentages of IBRs, and are standard configurations and combinations of services helpful in simplifying operational decision-making? | F5: 2 | P5: 2 | T5: 2
C6: =C5+1 -> 5 | D6: What recommendations for standard IBR frequency characteristics and responses should be identified to help system design? For example, should a contribution to damping be mandatory at certain frequencies?
C7: =C6+1 -> 6 | D7: What requirements (e.g. impedance) should be placed on IBRs to control negative sequence currents for protection and harmonics suppression?
A8: Stability | B8: St1 - Tools for real-time operation of IBR dominated systems | C8: =C7+1 -> 7 | D8: What approaches can be taken to track the dynamic response of IBR-dominated systems near real time and detect any emerging stability problems? | F8: 1 | G8: 2 | J8: 1
B9: St2 - Methods for planning and operation of low-inertia systems | C9: =C8+1 -> 8 | D9: What methods, including data types, and analyses can be used to identify the risk of poorly damped IBR-induced oscillations in planning studies and trace their root cause?
C10: =C9+1 -> 9 | D10: What analytical tools and models should be provided to planners and operators for robust assessment of system performance in IBR-dominated power grids? | F10: 2 | G10: 2 | J10: 3 | T10: 2
C11: =C10+1 -> 10 | D11: What methods and tools should be used in planning and/or operation to determine the appropriate mix, location, and capabilities of grid-forming and grid-following inverters to mitigate stability problems for a given power system? | T11: 3
C12: =C11+1 -> 11 | D12: In what form and fidelity should the original equipment manufacturers/developers and system operators exchange the IBR and grid models for comprehensive stability assurance of IBR-dominated grids? | J12: 1
A13: DER System Services | B13: D3 - Bulk system services | C13: =C12+1 -> 12 | D13: What mechanisms and appropriate aggregate DER representations and data are necessary to account for DERs in system-wide operation and planning, and in techno economic evaluation? | H13: 3 | L13: 1 | O13: 1 | V13: 3 | X13: 1
C14: =C13+1 -> 13 | D14: How can system operators quantify the bulk-level energy and service opportunities from DER, and how can these services be shared among distribution operators, bulk operators, aggregators and (where applicable) customers? | H14: 1 | L14: 1 | O14: 1 | V14: 3 | W14: 1 | X14: 1
C15: =C14+1 -> 14 | D15: How can bulk-level services provided by DER be valued as a compromise between simplicity and, for example, a complex full cost-reflective approach? | H15: 2 | L15: 1 | V15: 1 | W15: 1 | X15: 1
A16: DER C&C | B16: D1 - DER Aggregation, measurement & control | C16: =C15+1 -> 15 | D16: What aggregate quantities must be monitored, screened, and validated to ensure reliable service provision from different DER categories and at what temporal and/or spatial resolution must these processes occur? | L16: 2 | O16: 2 | W16: 1 | X16: 2
C17: =C16+1 -> 16 | D17: What is the communication capability needed to support monitoring and coordination of DER in terms of reliability, latency, bandwidth and (cyber) security? | L17: 3
B18: D2 - Data and control architecture | C18: =C17+1 -> 17 | D18: What is a scalable data architecture for DER monitoring, modelling, and coordination in real-time that would be suitable for the control room? | L18: 2
C19: =C18+1 -> 18 | D19: What are the relative merits of different coordination architectures for DER with respect to appropriateness for device characterizations, accounting for practical constraints around communication and computation, different types of aggregators, different DER objectives and heterogeneity and existing distribution system operator/system operator schemes? | L19: 2 | W19: 1
A20: CROF | B20: C1 - Flexibility assessment | C20: =C19+1 -> 19 | D20: How can the capabilities of grid-enhancing technologies (such as FACTS,SPS, RAS, DLR, PFC, WAMPAC) be integrated into the operational decision-making process? | F20: 1
C21: =C20+1 -> 20 | D21: How can grid topology be flexibly adapted to be reliably integrated into the operational decision-making process with outage scheduling, transfer limit increase, and post contingency remedial actions? | G21: 3 | I21: 2 | K21: 2
C22: =C21+1 -> 21 | D22: What applications are required to assess adequate flexibility from all resources, including those on the transmission, distribution and coupled energy systems (e.g., heat, electric vehicles, etc.) in the near term, and how can these resources be applied to address uncertainty during real-time applications? | I22: 2 | M22: 1 | O22: 2 | U22: 2 | V22: 3 | X22: 2
B23: C2 - Data and digital architecture | C23: =C22+1 -> 22 | D23: What type of digital architecture is best placed to enable modularity and the variety of software required to operate a control room in real time, near-real time, and in auto pilot mode?
C24: =C23+1 -> 23 | D24: What is the best way to integrate large datasets, streaming information, and historical system performance to create actionable operational insights in an increasingly complex environment with multiple phenomena occurring within overlapping timescales? | E24: 1 | I24: 2
B25: C3 - Security assessment | C25: =C24+1 -> 24 | D25: How can the risk of high-impact low-probability events (weather-related and otherwise) be incorporated into security assessments in real time and operations planning? | E25: 2 | G25: 1 | I25: 1
C26: =C25+1 -> 25 | D26: What metrics and their definitions (system strength, inertia, or others) need to be appropriately monitored or calculated to assess system dynamic behavior in real time, and what monitoring capabilities are necessary to support these assessments? | F26: 1
B27: C4 - Visualization | C27: =C26+1 -> 26 | D27: What improvements can be made to predictive tools and visualization methodologies in operational applications within the control room to support decision-making in real-time operations? | I27: 2 | K27: 4 | U27: 1
B28: C5 - Forecasting | C28: =C27+1 -> 27 | D28: How can risk-based methods (e.g. probabilistic forecasting techniques) be better incorporated into operational decision-support tools and used consistently across multiple stages (e.g., real-time, day ahead, intraday planning)? | E28: 2 | I28: 2 | N28: 1
A29: System Services | B29: SS1 - System needs | C29: =C28+1 -> 28 | D29: What system services are needed across different timescales and to the extent that services coexist within the same timescale, how should these services be designed to avoid competition and overlap? | X29: 1
C30: =C29+1 -> 29 | D30: What are the needs of a power system expressed in technologically neutral form and how do these needs map to services that any resource (including data centers, other IBRs, DERs, high-voltage direct current links, etc.) can provide? | L30: 2 | M30: 2 | O30: 2 | X30: 1
C31: =C30+1 -> 30 | D31: How can system performance requirements be translated into reliable new technology solutions? | M31: 2 | P31: 3
C32: =C31+1 -> 31 | D32: For each service, how feasible is it to provide from IBR, what “cost” does it add, what limitations exist on its magnitude and duration and what are the trade-offs between the provision of services?
B33: SS2 - Services design | C33: =C32+1 -> 32 | D33: How should system restoration services be structured and organized in systems with few or no synchronous machines, relying on IBR technologies and variable energy resources?
C34: =C33+1 -> 33 | D34: How should the definitions of services for IBR-dominated grids be structured and can standard services and standard characteristics be defined as reasonable for large and small IBRs and across variable renewable energy, storage, demand response interfaces and for differing procurement mechanisms? | L34: 2 | M34: 2 | P34: 1 | V34: 2
C35: =C34+1 -> 34 | D35: What methods could determine the need, sufficiency, and locational nature of IBR voltage control and system strength services for a given area? | F35: 1 | M35: 1
C36: =C35+1 -> 35 | D36: What models and methods, including testing, are necessary to quantify the ability of variable renewable energy to provide essential reliability services to the grid, and how do system operators quantify the value of these reliability services (for example, as an input to system-specific market/incentive design questions)? | E36: 1 | F36: 1 | L36: 2 | M36: 2 | O36: 1 | P36: 2 | S36: 1 | U36: 1 | V36: 2 | X36: 1
C37: =C36+1 -> 36 | D37: What system services can be designed to enable response from IBRs that can be a substitute for inertia (i.e. very fast frequency response)? | M37: 3 | P37: 3
A38: Planning | B38: P2 - Resource Adequacy | C38: =C37+1 -> 37 | D38: What studies and metrics are required to identify long-term scarcity of resources (capacity, energy, flexibility etc.) to maintain reliability? | E38: 2
C39: =C38+1 -> 38 | D39: How should grid enhancing technologies be included in the planning processes? | J39: 1
C40: =C39+1 -> 39 | D40: What technical models need to be added to long-term planning methods and studies to consider other reliability services in addition to traditional resource adequacy and deliverability? For example, how should sufficient restoration capability be modeled in long-term reliability studies? | E40: 1 | H40: 1 | J40: 1 | V40: 2 | X40: 2
C41: =C40+1 -> 40 | D41: What studies and metrics are required to evaluate resource adequacy with hybrid plants (e.g., photovoltaics-plus-storage) and virtual power plants? | H41: 2 | L41: 1 | O41: 1 | X41: 1
B42: P1 - Planning under uncertainty | C42: =C41+1 -> 41 | D42: What additional probabilistic planning methods and tools are necessary for planning a power system with a high share of IBRs and in particular, variable renewable energy resources? | E42: 3 | J42: 1 | X42: 2
C43: =C42+1 -> 42 | D43: What additional planning models and methods are needed to plan for various levels of uncertainty and no-regrets investments in a paradigm of increasing electrification and growing IBR and DER penetrations? | E43: 2 | H43: 2 | I43: 1 | L43: 1 | O43: 1 | P43: 1 | R43: 2 | V43: 2
C44: =C43+1 -> 43 | D44: What changes can be incorporated into the transmission planning process, especially inter-regional planning, to unlock multi-value system benefits and accommodate new drivers of uncertainty (e.g., large growth due to electrification or low growth due to increased use of DERs)? | E44: 2 | O44: 1 | V44: 2 | W44: 1
C45: =C44+1 -> 44 | D45: What methods, processes, and products (e.g. services) can support effective valuation, integration, and procurement of long-duration energy storage? | L45: 2
C46: =C45+1 -> 45 | D46: What additional load and resource forecasting models are necessary to account for electrification, including large loads (e.g., data centers), coupling of the transportation and building sectors, and demand-side flexibility? | H46: 2 | V46: 1
B47: P3 - Extreme events | C47: =C46+1 -> 46 | D47: What additional methods, tools, and metrics are necessary to incorporate resilience concepts and the ability to recover and adapt to adverse conditions, considering uncertain future states into planning a power system with a high share of renewables?
C48: =C47+1 -> 47 | D48: How do system operators adequately account for the overall system impact of extreme events in planning studies, particularly those that impact the system with a high share of flexible resources in both supply and demand (wind, solar, demand-side flexibility)? | E48: 1 | G48: 1
C49: =C48+1 -> 48 | D49: What additional planning models and methods are needed to plan for a system that can withstand expected or unexpected lulls (e.g., an extended wind drought, or a dunkelflaute)? | E49: 2 | G49: 1

Sheet Rationale
A1: Abstract_Index | B1: Document Title | C1: Abstract | D1: RA2025_ID | E1: RA_Question | F1: Evaluator_Affinity_Level | G1: Evaluator_Score | H1: adjudicated_level | I1: Final_Reason | J1: Why this score was assigned to the abstract? | K1: Why does this abstract fall below the next relevance level?
A2: 65 | B2: Cooperative Hierarchical Control of Isolated Microgrids Considering Energy Storage System Aggregation | C2: =_xlfn.XLOOKUP(A2,'Abstracts List'!A:A,'Abstracts List'!C:C) -> The integration of numerous energy storage systems (ESSs) improves the reliable and economic operation of microgrids but also enlarges the burden of control and communication systems. This article proposes a cooperative hierarchical control for isolated microgrids with ESSs, which fully frees from the centralized paradigm and is therefore superior in flexibility and scalability. Firstly, the ESS cooperative control based on the distributed frequency controller is introduced for the state of charge (SoC) balance and the frequency regulation. Then, the ESS aggregation is considered. The aggregated ESS model is established and the real-time model parameters are derived by proposed distributed state observers. Finally, energy management is employed to allocate the output power between generators and the aggregated ESS. A detailed theoretical analysis of the dynamic and steady-state performance of proposed controllers and observers is provided. Simulations on the IEEE 33-bus and the 69-bus system verify the effectiveness of proposed methods. | D2: 12 | E2: What mechanisms and appropriate aggregate DER representations and data are necessary to account for DERs in system-wide operation and planning, and in techno economic evaluation? | F2: Low | G2: {=_xlfn.XLOOKUP(D2, 'Question context'!$C$2:$C$49, _xlfn.XLOOKUP(A2, 'Question context'!$E$1:$Y$1, 'Question context'!$E$2:$Y$49))} -> 1 | H2: Moderate | I2: Most models rated this strongly (60â€“86). I resolved high because the paper directly develops an aggregated ESS representation and derives real-time model parameters via distributed observers, which is closely aligned with aggregate DER representations for operation. The score is slightly reduced because planning and techno-economic evaluation are not central themes. | J2: There are some potential links between the content of this research paper and the G-PST research question. In particular Microgrids can be considered to be DERs to some extent and by controlling them you are potentially making them somewhat like an aggregated DER resource. Some of the concepts like observability mentioned in the abstract of the paper are also potentially of interest. | K2: There is nothing direct within the abstract of the paper to link directly to aggregation and DERs. The links are at best second hand. The overall application of the paper is on a test system not a real system and there is mention of the word theoretical which is not a confidence building term with respect to a real application.
A3: 94 | B3: An AC-Feasible Linear Model in Distribution Networks With Energy Storage | C3: =_xlfn.XLOOKUP(A3,'Abstracts List'!A:A,'Abstracts List'!C:C) -> With the increasing deployment of distributed energy resources (DERs), dispatching DERs subject to operational constraints in distribution networks draws much attention. One challenge is the non-convexities in 1) system-wide AC power flow constraints and 2) the individual complementarity constraint of energy storage. To resolve this challenge, this paper studies an AC-feasible linear model in distribution networks with energy storage, including its formulation, analysis, and applications. First, an AC-feasible linear model is formulated as a set of linear constraints on controllable DERs and uncontrollable power demand by 1) converting the non-convex system-wide constraints into linear constraints based on the Brouwer's fixed-point theorem and the second-order Taylor expansion, and 2) replacing the non-convex individual complementarity constraint of energy storage with one properly designed linear constraint. Furthermore, to analyze the power demand level at which the proposed linear model can provide a solution, this paper proposes an examination-based projection method under the Monte Carlo framework to handle projections of thousands of dimensions from linear constraints over time periods. Finally, the potential applications of our AC-feasible linear model are discussed. Numerical experiments are conducted in the IEEE 33-bus and 136-bus test systems to demonstrate the effectiveness of the proposed methods. | D3: 13 | E3: How can system operators quantify the bulk-level energy and service opportunities from DER, and how can these services be shared among distribution operators, bulk operators, aggregators and (where applicable) customers? | F3: Low | G3: {=_xlfn.XLOOKUP(D3, 'Question context'!$C$2:$C$49, _xlfn.XLOOKUP(A3, 'Question context'!$E$1:$Y$1, 'Question context'!$E$2:$Y$49))} -> 1 | H3: Moderate | I3: Most models rated this moderate-to-high because the paper develops an AC-feasible dispatch model for DERs and storage, which helps quantify feasible DER capabilities at a system level. I discounted the highest scores because the abstract does not address bulk-level service valuation or how benefits are shared among bulk operators, DSOs, aggregators, and customers. | J3: There are some potential links between the content of this research paper and the G-PST research question. In particular this is about DERs and accounting for the constraints that DERs have - this is linked with the primary objective of the G-PST research question which is quantification of services and constrainst in the distribution system are a key to understand that. There is also potential applications is mentioned in the abstract of the papaer which is at least accepting application may be important. | K3: The focus of the paper is on the distribution network and not the transmissio network - in order for it t be scored higher it would need to focus on the transmission system. The paper abstract is very focussed on the details of the formulation of an optimisation prolem and some theory and not on the formulation of an real applied problem. Test results are from a test system and not a real sysytem with no obvius link to real industry stakeholders and/or real applications focussed work.
A4: 194 | B4: Analysis of Long-Term Indicators in the British Balancing Market | C4: =_xlfn.XLOOKUP(A4,'Abstracts List'!A:A,'Abstracts List'!C:C) -> Proactive participation of uncertain renewable generation in the day-ahead (DA) wholesale market effectively reduces the system marginal price and carbon emissions, whilst significantly increasing the volumes of real-time balancing mechanism prices to ensure system security and stability. To solve the conflicting interests over the two timescales, this article: 1) proposes a novel hierarchical optimization model to align with the actual operation paradigms of the hierarchical market, whereby the capacity allocation matrix is adopted to coordinate the DA and balancing markets; 2) mathematically formulates and quantitatively analyses the long-term driving factors of balancing actions, enabling system operators (SOs) to design efficient and well-functioning market structures to meet economic and environmental targets; 3) empowers renewable generating units and flexible loads to participate in the balancing market (BM) as Ã¢â‚¬ËœactiveÃ¢â‚¬â„¢ actors and enforces the non-discriminatory provision of balancing services. The performance of the proposed model is validated on a modified IEEE 39-bus power system and a reduced GB network. Results reveal that with effective resource allocation in different timescales of the hierarchical market, the drop speed of balancing costs soars while the intermittent generation climbs. The proposed methodology enables SOs to make the most of all resources available in the market and balance the system flexibly and economically. It thus safeguards the climate mitigation pathways against the risks of substantially higher balancing costs. | D4: 35 | E4: What models and methods, including testing, are necessary to quantify the ability of variable renewable energy to provide essential reliability services to the grid, and how do system operators quantify the value of these reliability services (for example, as an input to system-specific market/incentive design questions)?Â | F4: Low | G4: {=_xlfn.XLOOKUP(D4, 'Question context'!$C$2:$C$49, _xlfn.XLOOKUP(A4, 'Question context'!$E$1:$Y$1, 'Question context'!$E$2:$Y$49))} -> 1 | H4: High | J4: There are potential links between the paper abstract and the G-PST research question. In particular the paper is addressing the british balancing market and the research question is asking can variable renewable energy provide services. The link if it is there is on the methods side. | K4: The potential links identified between the paper abstract and the G-PST research question are possibling misleading so scoring any higher is simply not justified. may not actually have anything of value
A5: 44 | B5: Hierarchical Control Strategy for Effective Virtual Frequency Responses of Multiple WPPs | C5: =_xlfn.XLOOKUP(A5,'Abstracts List'!A:A,'Abstracts List'!C:C) -> When renewable energy-based generations are increasing, they are subject to cause frequency stability problems in a power system. To solve this problem, various virtual inertial control methods (VICMs) have been recently developed. However, they all have dealt not with the steady-state frequency stability, but only with dynamic frequency stability issues. In particular, the wind power plants (WPPs) operated by these VICMs can only provide a similar inertial response (IR) to that by conventional synchronous generators without providing the primary frequency response (PFR). This results in lowering the settling frequency (SF) below the maximum steady-state frequency deviation (MSSD) band. This paper proposes the new hierarchical control strategy for the WPPs, which are operated by three virtual frequency response control methods (VFRCMs) to provide both IR and PFR. Firstly, the VFRCM-1 provides virtual IR. Next, the VFRCM-2 increases the output power from the WPPs to prevent the frequency drop, which can occur after the frequency nadir is arrested. Finally, the VFRCM-3 makes the WPPs possible to raise the SF above the MSSD band by providing the virtual PFR. The effectiveness of proposed hierarchical control strategy is verified by several case studies on the IEEE 39-bus test system with the high penetration of renewables. | D5: 3 | E5: How could the IBR control paradigm change from replicating synchronous machines to exploiting wider IBR flexibility without introducing integration challenges during the transition? | F5: Low | G5: {=_xlfn.XLOOKUP(D5, 'Question context'!$C$2:$C$49, _xlfn.XLOOKUP(A5, 'Question context'!$E$1:$Y$1, 'Question context'!$E$2:$Y$49))} -> 1 | H5: High | I5: Model scores were consistently high (70â€“84). The abstract clearly moves beyond simple synchronous-machine-like inertia emulation by adding layered virtual inertial and primary frequency response from wind plants. I kept the score below the maximum because it does not really address transition/integration challenges, only the control paradigm shift itself. | J5: There is a potential link between the paper astract which is focussed on controlling wind power plants to provide so called virtual frequency response and the G-PST research question which is focussed on the IBR control paradigm. The assumption is that IBR control and WPP control share a lot in common. | K5: The link identified may not result in any synergy between the research being reported in the paper and the G-PST research question. While IBRs and WPPs do share some things in common the link in this instance may not actually amount to anything of interest. There is also no mention of any real application or involvement of system operators and industry and the results are on a test system not a real system.
A6: 81 | B6: Virtual ProsumersÃƒÂ¢Ã¢â€šÂ¬Ã¢â€žÂ¢ P2P Transaction Based Distribution Network Expansion Planning | C6: =_xlfn.XLOOKUP(A6,'Abstracts List'!A:A,'Abstracts List'!C:C) -> The deployment of prosumers with distributed energy resources (DERs) has facilitated the prosumer-centric transactive market, giving rise to the consequent necessity for the coordination between prosumers and the distribution networks. This paper proposes an incentive-based expansion planning method considering virtual peer-to-peer (P2P) transaction among prosumers, which is characterized as a tri-level planning-operation-transaction framework. Each prosumer optimizes its internal response of DERs and external P2P transaction jointly, formulating virtual P2P transaction. Under such a paradigm, the distribution company (DISCO) identifies the optimal expansion planning in the network assets, while the independent distribution system operator (IDSO) is responsible for the optimal operation of the expanded distribution networks. To derive appropriate incentives for each prosumer, the DISCO and IDSO allocate long-term investment network charges and short-term operation network charges on prosumers, along with the designed financial transmission rights coupling multiple time scales. Through such incentives, self-profit driven virtual transactions can relieve operation problems and postpone expansion planning, acting as a short-term alternative. Moreover, a risk-based approach is proposed for prosumer to flexibly change strategy according to different risk preference. Finally, results from the case study demonstrate the superiority and effectiveness of the proposed method in the collaborative application of virtual transaction in the expansion planning. | D6: 13 | E6: How can system operators quantify the bulk-level energy and service opportunities from DER, and how can these services be shared among distribution operators, bulk operators, aggregators and (where applicable) customers? | F6: Low | G6: {=_xlfn.XLOOKUP(D6, 'Question context'!$C$2:$C$49, _xlfn.XLOOKUP(A6, 'Question context'!$E$1:$Y$1, 'Question context'!$E$2:$Y$49))} -> 1 | H6: High | I6: Most models rated this moderately to strongly relevant because the paper quantifies DER/prosumer transactions, allocates network charges, and coordinates value sharing among prosumers, DISCO, and IDSO. I discounted the highest score because the work is distribution-centric and does not truly quantify bulk-level opportunities or sharing with bulk operators in a full transmission sense. | J6: DERs and one of the stakeholders the prosumer are identified in the abstact of the papaer which has potential links to quantification of services frm DERs and sharing of these amoung other stakeholders. | K6: The identified G-PST research question is in the services area yet the paper is tackling a plannig problem so the links identified are at best tangential and at worst non existent. The whole area of transactive energy and markets is out of scope for G-PST research question so that is a poor indicator of strong links. The application domain and/or time frame of the paper and the G-PST research question may differ it loks like the paper is targeting planning while the G-PST research question i sin the operations time frame.
A7: 241 | B7: Adaptive Weighted Combination Approach for Wind Power Forecast Based on Deep Deterministic Policy Gradient Method | C7: =_xlfn.XLOOKUP(A7,'Abstracts List'!A:A,'Abstracts List'!C:C) -> Accurate wind power forecast (WPF) is critical for ensuring secure and economic operation of a power system, and combination forecasting approaches for WPF have been proved effective on attaining accurate forecasting results. However, the weights in a combination forecasting model are usually predetermined based on the global performance on the training set, limiting the adaptability of the model to different scenarios. To further enhance the accuracy and effectiveness of the combination forecasting approaches, this article proposes an adaptive weighted combination forecasting approach based on the deep deterministic policy gradient (DDPG) so as to consider the local behavior accompanied by the change of external environment. Three sub-models are first selected considering the equal-likelihood and dispersion indices to construct a combination model. Then, the DDPG agent is trained to act as a weight generator by interacting with the environment and to maximize the reward. Thus, the DDPG agent can perceive the environmental changes online and dynamically weight the sub-models to attain accurate forecasting results. Case studies demonstrate that the forecasting accuracy of the proposed approach is better than that of all sub-models and several benchmark combination forecasting approaches. | D7: 27 | E7: How can risk-based methods (e.g. probabilistic forecasting techniques) be better incorporated into operational decision-support tools and used consistently across multiple stages (e.g., real-time, day ahead, intraday planning)? | F7: Low | G7: {=_xlfn.XLOOKUP(D7, 'Question context'!$C$2:$C$49, _xlfn.XLOOKUP(A7, 'Question context'!$E$1:$Y$1, 'Question context'!$E$2:$Y$49))} -> 1 | H7: High | I7: This is one of the strongest matches. The paper directly proposes an adaptive forecasting method using DDPG for online weighting under changing conditions, which aligns well with incorporating advanced predictive/risk-aware methods into operational decision support. I tempered the very high scores slightly because the abstract does not explicitly address consistency across multiple operational stages such as day-ahead, intraday, and real-time. | J7: This is an incremental piece of research that does not directly address and of the G-PST research questions but does paotentially have some links to some aspects of the research agenda. | K7: There are no real practical applications. It is mainly methological and incremental and it is at best a small potential contribution to a very secondary aspect of the much more impactful research question.
A8: 94 | B8: An AC-Feasible Linear Model in Distribution Networks With Energy Storage | C8: =_xlfn.XLOOKUP(A8,'Abstracts List'!A:A,'Abstracts List'!C:C) -> With the increasing deployment of distributed energy resources (DERs), dispatching DERs subject to operational constraints in distribution networks draws much attention. One challenge is the non-convexities in 1) system-wide AC power flow constraints and 2) the individual complementarity constraint of energy storage. To resolve this challenge, this paper studies an AC-feasible linear model in distribution networks with energy storage, including its formulation, analysis, and applications. First, an AC-feasible linear model is formulated as a set of linear constraints on controllable DERs and uncontrollable power demand by 1) converting the non-convex system-wide constraints into linear constraints based on the Brouwer's fixed-point theorem and the second-order Taylor expansion, and 2) replacing the non-convex individual complementarity constraint of energy storage with one properly designed linear constraint. Furthermore, to analyze the power demand level at which the proposed linear model can provide a solution, this paper proposes an examination-based projection method under the Monte Carlo framework to handle projections of thousands of dimensions from linear constraints over time periods. Finally, the potential applications of our AC-feasible linear model are discussed. Numerical experiments are conducted in the IEEE 33-bus and 136-bus test systems to demonstrate the effectiveness of the proposed methods. | D8: 12 | E8: What mechanisms and appropriate aggregate DER representations and data are necessary to account for DERs in system-wide operation and planning, and in techno economic evaluation? | F8: Low | G8: {=_xlfn.XLOOKUP(D8, 'Question context'!$C$2:$C$49, _xlfn.XLOOKUP(A8, 'Question context'!$E$1:$Y$1, 'Question context'!$E$2:$Y$49))} -> 1 | H8: High | I8: There is strong cross-model agreement that this is one of the best matches. The paper proposes aggregate linear representations of controllable DERs and storage with AC-feasible network constraints for operation/planning. I stopped short of an even higher score because mechanisms, data requirements, and techno-economic evaluation are not deeply developed. | J8: There may be some potential link between the research as described in the abstract and the G-PST research question. This link is embodied in the focus on DErs in both the paper and the research question but the link is at best tenous. | K8: An incremental piece of research is reported in the abstract of the paper and it is not directly related to the G-PST research question. It is also fixated on methodology and only conducts some numerical experiments with no sign of a real application.
A9: 45 | B9: Time Aggregation in Presence of Multiple Variable Energy Resources | C9: =_xlfn.XLOOKUP(A9,'Abstracts List'!A:A,'Abstracts List'!C:C) -> This paper proposes a new time aggregation method that can properly reflect the spatial aspect of the data sources alongside their temporal behaviour when multiple variable energy resources are involved. Each representative period, constructed by the proposed method, can include more than one representative day, which, in itself, represents a group of data sources that are highly associated with each other. It also preserves the spatial relationship among data sources as a whole by constructing a hybrid centroid. Two case studies, each with different data sources and networks, with and without energy storage, are considered for this study. In the second case, we add an storage to reflect the significance of preserving shape of patterns in the representative periods. The duration curves of wind farms' and solar farms' generations, electricity demand, and net demand are used as data-based evaluation indices to compare the performance of the proposed method against other approaches. In addition, an IEEE 24-bus and a 6-bus test system are considered for the case studies. Two model-based evaluation indices are used to measure the performance of the clustering methods, including the power flow of all the lines in the system and the annual operation cost of the system. In addition, the performance of the proposed method in the presence of energy storage is evaluated and compared with existing methods. | D9: 12 | E9: What mechanisms and appropriate aggregate DER representations and data are necessary to account for DERs in system-wide operation and planning, and in techno economic evaluation? | F9: Low | G9: {=_xlfn.XLOOKUP(D9, 'Question context'!$C$2:$C$49, _xlfn.XLOOKUP(A9, 'Question context'!$E$1:$Y$1, 'Question context'!$E$2:$Y$49))} -> 1 | H9: High | I9: This is one of the strongest matches. Multiple models recognized that the paper proposes an aggregate representation method using representative periods and hybrid centroids for variable resources and demand, directly relevant to aggregate DER-like representations in planning and techno-economic evaluation. I discounted the highest scores slightly because the abstract is not explicitly DER-focused and emphasizes VREs and storage rather than broad DER mechanisms. | J9: This is a methods based paper that has some small potential link to the research agenda. The research question is seeking methods to use when trying to account for DERs in planning and techno econmic analysis and this paper may be useful when dealing with aggregation of the spatial /DER aspects. | K9: This is a paper with an potential link to some aspects of the G-PST research agenda in the DER space. It shares data and aggregation of variable renewable energy within the scope of the paper. It is at best an icremental contribution and has only some small case studies that are not obviously directly related to the research agenda.
A10: 228 | B10: Reduced Voltage-Dependency by Categorical Location Information and Distance Along Street Metric for Meter-Transformer Mapping in Distribution Systems | C10: =_xlfn.XLOOKUP(A10,'Abstracts List'!A:A,'Abstracts List'!C:C) -> Deep penetration of distributed energy resources (DERs) and electric vehicles (EVs) introduce benefits but may cause the overloading of service transformers in distribution networks. Such situations require real-time transformer loading information, where an accurate mapping between smart meters and distribution transformers is a prerequisite, e.g., summing the downstream smart meter consumptions. Due to arbitrary curvature in streets, we propose to employ a density-based clustering based on voltage magnitudes (continuous) and street name (categorical) information. However, a density-based approach may only be able to localize a meter to a street segment. Hence, we use a second-stage spectral clustering with distance along the street (DAS), a novel feature, to obtain meter clusters, each with a common parent transformer. For mapping transformers to meter clusters, we use the nearest cluster center approach based on the location since voltage measurements may not be available at transformers. Moreover, we provide a theoretical guarantee for such an approach. Finally, we illustrate the usefulness of the proposed algorithm on long streets, which is a challenging scenario due to many possible incorrect combinations of meter-transformer mapping. The proposed algorithm has been tested on modified IEEE 8-, $6{9}$-, 123-bus test systems and real distribution feeders from a utility in the Southwestern United States, demonstrating outstanding performance. | D10: 15 | E10: What aggregate quantities must be monitored, screened, and validated to ensure reliable service provision from different DER categories and at what temporal and/or spatial resolution must these processes occur? | F10: Low | G10: {=_xlfn.XLOOKUP(D10, 'Question context'!$C$2:$C$49, _xlfn.XLOOKUP(A10, 'Question context'!$E$1:$Y$1, 'Question context'!$E$2:$Y$49))} -> 1 | H10: High | I10: This is one of the strongest matches. The paper is directly about obtaining accurate transformer-level aggregation from smart meters so operators can monitor transformer loading in real time, which aligns with identifying aggregate quantities and spatial resolution needed for reliable service provision. I moderated the very highest scores slightly because it focuses on one aggregate quantity and mapping method rather than a broader framework of monitored DER categories and validation processes. | J10: This research paper addresses a distribution level challenge that can have some impact on the higher level transmission related problems that are the focus of the G-PST research agenda. It does however have a good potential link to a real pratctical problem as indicated by the real distribution untility application. | K10: The ppaer aspect does not address a G-PST research question in and direct way - it is focussed on the distribution system and not the transmission system therefore its link to the G-PST research question is minimal. While there is an application in the ppaer it is not on the transmission system so that is a big weakness with resect to a strong link with the G-PST research question.
A11: 134 | B11: High-Dimensional Feature Selection for Power System Congestion Event Prognosis With Enhanced Evolutionary Computation | C11: =_xlfn.XLOOKUP(A11,'Abstracts List'!A:A,'Abstracts List'!C:C) -> Power system congestion event prognosis (CEP) based on multivariate time series (MTS) learning is an effective way to improve the warning abilities against risky situations. However, it is still challenging to decide which measurement sequences of system variables should be selected to train MTS learning-based CEPs models, especially when facing high-dimensional candidate features from power systems. Focusing on this issue, this paper proposes a novel high-dimensional feature selection (FS) method to identify and select variables that contain beneficial data patterns for the prognosis of network congestion events. A wrapper framework embedded with multiple MTS learning models is first built to treat FS as a combinatorial optimization task and receive MTS as inputs directly without sequence compressions. Then, to improve the combinatorial optimization efficiency and FS results in the high-dimensional case, a hybrid structure called enhanced evolutionary computation (EEC) is developed by combining with information theory-based feature priority scores, which play the role of semi-guidance in the iterative search. Test results on both the real-world and synthetic datasets validate the effectiveness of the developed EEC structure and show that the selected features by the proposed FS method are more beneficial in identifying the early patterns of network congestion events, thus contributing to efficient and accurate CEP for power systems. | D11: 21 | E11: What applications are required to assess adequate flexibility from all resources, including those on the transmission, distribution and coupled energy systems (e.g., heat, electric vehicles, etc.) in the near term, and how can these resources be applied to address uncertainty during real-time applications? | F11: Moderate | G11: {=_xlfn.XLOOKUP(D11, 'Question context'!$C$2:$C$49, _xlfn.XLOOKUP(A11, 'Question context'!$E$1:$Y$1, 'Question context'!$E$2:$Y$49))} -> 2 | H11: Low | I11: The paper uses multivariate operational data and uncertainty-related event prognosis, but it does not assess flexibility from transmission, distribution, EVs, heat, or other coupled energy resources, nor how such flexibility is deployed in real time. I therefore treated the few moderate scores as overextensions and kept the final score low. | J11: The research in this paper has a reasonably good link to the G-PST research question. The paper describes a method to identify features that can be used to enhance the potential of harnessing flexibility resources. There is reference to a real world test results which is encouraging. | K11: While the links are potentially strong between the paer and the research question they are not direct. The paper addresses congestion but the research question is focussed on flexibility - congestion has an impact of flexibility but i snot a oneto one relationship. No clear link or working relationship with a system operator is evident.
A12: 231 | B12: Centralized Distributionally Robust Chance-Constrained Dispatch of Integrated Transmission-Distribution Systems | C12: =_xlfn.XLOOKUP(A12,'Abstracts List'!A:A,'Abstracts List'!C:C) -> Coordinated dispatch of integrated transmission-distribution systems (ITDs) continues to be a hotspot due to the growing demand-side flexibility. Decentralized optimization, which has been widely studied, does not conform to the current hierarchical framework of power system operation. This paper proposes a centralized distributionally robust chance-constrained dispatch model for ITDs. The transmission system operator considers the flexible ranges of large-scale distributed energy resources (DERs) in distribution systems via flexibility aggregation. A price-guided flexibility model is proposed to describe the temporally coupled aggregate flexibility of distribution systems. It is constructed by filtering those constraints with a high probability of activeness in the ITD dispatch problem, reducing the number of constraints from quadratic to linear with the number of divided time slots while maintaining high accuracy. Furthermore, we use the data-driven distributionally robust chance constraint to deal with the uncertainty from both renewable generations and the flexibility of DERs. Numerical simulations on IEEE test systems verify the effectiveness of the proposed methods. | D12: 39 | E12: What technical models need to be added to long-term planning methods and studies to consider other reliability services in addition to traditional resource adequacy and deliverability?Â For example, how should sufficient restoration capability be modeled in long-term reliability studies?Â | F12: Moderate | G12: {=_xlfn.XLOOKUP(D12, 'Question context'!$C$2:$C$49, _xlfn.XLOOKUP(A12, 'Question context'!$E$1:$Y$1, 'Question context'!$E$2:$Y$49))} -> 2 | H12: Low | I12: The paper does not address long-term planning for broader reliability services such as restoration capability. I gave slight credit for modeling flexibility under uncertainty, but resolved the conflict strongly downward because the core planning-and-restoration focus is absent. | J12: There is a potential relationshio between the focus of the paper and the G-PST research agenda. The paper focusses on the transmission distribution interface which is important in the DER part of the research agenda and the specific research question is looking into how reliability services in planning can account for deliverability. | K12: The research in the paper only relates to a small part of the research question and there are no signs of real practical application. It is also not clear if the ppaer can provide real planning related benefits as it is really focussed on operations so more work would need to be done to bring this research in the paper closer to te practical G-PST research question.
A13: 212 | B13: Comparative Analysis of the Power Output Capabilities of Grid-Following and Grid-Forming Inverters Considering Static, Dynamic, and Thermal Limitations | C13: =_xlfn.XLOOKUP(A13,'Abstracts List'!A:A,'Abstracts List'!C:C) -> This article investigates the maximum transferable power (MTP) of inverter-based resources (IBRs) and provides the output capability curves (OCCs) of grid-tied grid-following inverters (GFLIs) and grid-forming inverters (GFMIs). To this end, in the first part of the article, mathematical equations for GFLI static, thermal, and phase-locked loop (PLL)-induced power transfer limits are derived in terms of the grid short-circuit ratio (SCR) and its X/R ratio. Then, considering other operational limitations, such as the IBR AC- and DC-side voltage limits, the OCC of the GFLI is obtained. Additionally, the impact of the reactive current and the reactive control mode on the OCC is further studied, and accordingly, an auxiliary control loop is proposed to maximize the GFLI MTP. In the second part of the article, a similar approach is employed to derive mathematical equations for GFMI static and thermal limits, and accordingly, the OCC of a GFMI is obtained. The effects of the variation of the voltage set-point of the GFMI on its OCC are then studied, and the superiority of GFMIs compared to GFLIs is shown in terms of the MTP capability. Eventually, several simulation and experimental cases are conducted to validate the obtained equations and OCCs for both grid-following and grid-forming control modes. | D13: 4 | E13: What are the appropriate inverter capabilities and, consequently, control design methods for operation in grids with high percentages of IBRs, and are standard configurations and combinations of services helpful in simplifying operational decision-making? | F13: Moderate | G13: {=_xlfn.XLOOKUP(D13, 'Question context'!$C$2:$C$49, _xlfn.XLOOKUP(A13, 'Question context'!$E$1:$Y$1, 'Question context'!$E$2:$Y$49))} -> 2 | H13: High | J13: Thematically the paper abstract aligns very well with the IBR research program of the G-PST research agenda and specifically the research reported in ths paper addresses capability and control design. It also deals with these issues accross the range of IBRs i.e. GFM and GFL. The focus of the paper is in addressing real issues and is not methodologically dominated which is another good sign. | K13: The paper stpos short of services and/or operational deceson making which limits its potential linkage to the G-pST research question. Although simulation results and experiments are noted it i snot clear if they are at the right scale and applicability to be truly useful nor is it clear if a utility and/or a system operator are involved.
A14: 44 | B14: Hierarchical Control Strategy for Effective Virtual Frequency Responses of Multiple WPPs | C14: =_xlfn.XLOOKUP(A14,'Abstracts List'!A:A,'Abstracts List'!C:C) -> When renewable energy-based generations are increasing, they are subject to cause frequency stability problems in a power system. To solve this problem, various virtual inertial control methods (VICMs) have been recently developed. However, they all have dealt not with the steady-state frequency stability, but only with dynamic frequency stability issues. In particular, the wind power plants (WPPs) operated by these VICMs can only provide a similar inertial response (IR) to that by conventional synchronous generators without providing the primary frequency response (PFR). This results in lowering the settling frequency (SF) below the maximum steady-state frequency deviation (MSSD) band. This paper proposes the new hierarchical control strategy for the WPPs, which are operated by three virtual frequency response control methods (VFRCMs) to provide both IR and PFR. Firstly, the VFRCM-1 provides virtual IR. Next, the VFRCM-2 increases the output power from the WPPs to prevent the frequency drop, which can occur after the frequency nadir is arrested. Finally, the VFRCM-3 makes the WPPs possible to raise the SF above the MSSD band by providing the virtual PFR. The effectiveness of proposed hierarchical control strategy is verified by several case studies on the IEEE 39-bus test system with the high penetration of renewables. | D14: 4 | E14: What are the appropriate inverter capabilities and, consequently, control design methods for operation in grids with high percentages of IBRs, and are standard configurations and combinations of services helpful in simplifying operational decision-making? | F14: Moderate | G14: {=_xlfn.XLOOKUP(D14, 'Question context'!$C$2:$C$49, _xlfn.XLOOKUP(A14, 'Question context'!$E$1:$Y$1, 'Question context'!$E$2:$Y$49))} -> 2 | H14: High | J14: This research paper abstract describes research that directly addresses the capability of wind plant to provide frequency control services. It also directly addresses the control problem and there are case studies on a a test network. These are all indicative of a solid lin with the G-PST research question. | K14: The paper falls short of being strongly linked to the G-PST research question as it does not appaer to be directed fully at the IBR aspects and it is also very focussed on the device rather than on the system itself. Furthermore the case study i son a small typical test network and there does not appaer to be any system operator involvement and/or any practical insights reported in the results.
A15: 174 | B15: Chance-Constrained Optimization Based PV Hosting Capacity Calculation Using General Polynomial Chaos | C15: =_xlfn.XLOOKUP(A15,'Abstracts List'!A:A,'Abstracts List'!C:C) -> Increased penetration of renewable resources and new loads have increased the uncertainty levels in low voltage distribution systems (LVDS). This requires considering LVDS planning, such as computing photovoltaics (PV) hosting capacity (HC), as a stochastic problem. Traditionally, PV HC is computed using the iterative Monte Carlo method, which requires solving the power flow equations thousands of times. This paper proposes a chance-constrained optimization-based hosting capacity calculation technique, which eliminates the necessity of repetitive solving of power flow equations. The intrusive general polynomial chaos expansion is used to translate the input uncertainties defined by their probability density function to the hosting capacity of the network without the necessity of sampling, linearizing the power flow equations, or applying any relaxations. Chance constraints are applied for nodal voltages and thermal overload as per the norms, where the system can be congested for a certain time without affecting the power quality. Numerical illustrations show the computational time to compute the stochastic PV hosting capacity of a real large scale LVDS, and for the majority of the feeders, it falls within 100 sec. Furthermore, the estimated PV HC using this stochastic optimal power flow was, on average, 20% higher than its deterministic counterpart. | D15: 42 | E15: What additional planning models and methods are needed to plan for various levels of uncertainty and no-regrets investments in a paradigm of increasing electrification and growing IBR and DER penetrations?Â | F15: Moderate | G15: {=_xlfn.XLOOKUP(D15, 'Question context'!$C$2:$C$49, _xlfn.XLOOKUP(A15, 'Question context'!$E$1:$Y$1, 'Question context'!$E$2:$Y$49))} -> 2 | H15: High | J15: While there is good alignment from a methods perspective the practical application of the research may only be on the distribution network which may limit the research work being reported in the papaer with respect to the G-PST transmssion system perspective and scope. There is also no sign of a real practical result and a path towrads deployment of the research to system operators.
A16: 134 | B16: High-Dimensional Feature Selection for Power System Congestion Event Prognosis With Enhanced Evolutionary Computation | C16: =_xlfn.XLOOKUP(A16,'Abstracts List'!A:A,'Abstracts List'!C:C) -> Power system congestion event prognosis (CEP) based on multivariate time series (MTS) learning is an effective way to improve the warning abilities against risky situations. However, it is still challenging to decide which measurement sequences of system variables should be selected to train MTS learning-based CEPs models, especially when facing high-dimensional candidate features from power systems. Focusing on this issue, this paper proposes a novel high-dimensional feature selection (FS) method to identify and select variables that contain beneficial data patterns for the prognosis of network congestion events. A wrapper framework embedded with multiple MTS learning models is first built to treat FS as a combinatorial optimization task and receive MTS as inputs directly without sequence compressions. Then, to improve the combinatorial optimization efficiency and FS results in the high-dimensional case, a hybrid structure called enhanced evolutionary computation (EEC) is developed by combining with information theory-based feature priority scores, which play the role of semi-guidance in the iterative search. Test results on both the real-world and synthetic datasets validate the effectiveness of the developed EEC structure and show that the selected features by the proposed FS method are more beneficial in identifying the early patterns of network congestion events, thus contributing to efficient and accurate CEP for power systems. | D16: 23 | E16: What is the best way to integrate large datasets, streaming information, and historical system performance to create actionable operational insights in an increasingly complex environment with multiple phenomena occurring within overlapping timescales? | F16: Moderate | G16: {=_xlfn.XLOOKUP(D16, 'Question context'!$C$2:$C$49, _xlfn.XLOOKUP(A16, 'Question context'!$E$1:$Y$1, 'Question context'!$E$2:$Y$49))} -> 2 | H16: High | J16: The focus of the paper on feature selection and training using large data sets is very well aligned with the underlying research question being asked for in the G-PST research agenda research question. Real world data along with synthetic data is also used in the research paper. | K16: While at a basic level the research paper abstract describes research that looks at large complex data sets to help in power system operations the focus of the paper is only on one aspect, congestion and there is also no sign that multiple time scales are addressed. Therefore the research paper is potentially well linked with a very specific aspect of the G-PSt resarch question but not the holistic aspects. No practical next steps are identified nor is there any sign of a real system operator and/or industry partner.
A17: 65 | B17: Cooperative Hierarchical Control of Isolated Microgrids Considering Energy Storage System Aggregation | C17: =_xlfn.XLOOKUP(A17,'Abstracts List'!A:A,'Abstracts List'!C:C) -> The integration of numerous energy storage systems (ESSs) improves the reliable and economic operation of microgrids but also enlarges the burden of control and communication systems. This article proposes a cooperative hierarchical control for isolated microgrids with ESSs, which fully frees from the centralized paradigm and is therefore superior in flexibility and scalability. Firstly, the ESS cooperative control based on the distributed frequency controller is introduced for the state of charge (SoC) balance and the frequency regulation. Then, the ESS aggregation is considered. The aggregated ESS model is established and the real-time model parameters are derived by proposed distributed state observers. Finally, energy management is employed to allocate the output power between generators and the aggregated ESS. A detailed theoretical analysis of the dynamic and steady-state performance of proposed controllers and observers is provided. Simulations on the IEEE 33-bus and the 69-bus system verify the effectiveness of proposed methods. | D17: 18 | E17: What are the relative merits of different coordination architectures for DER with respect to appropriateness for device characterizations, accounting for practical constraints around communication and computation, different types of aggregators, different DER objectives and heterogeneity and existing distribution system operator/system operator schemes? | F17: Moderate | G17: {=_xlfn.XLOOKUP(D17, 'Question context'!$C$2:$C$49, _xlfn.XLOOKUP(A17, 'Question context'!$E$1:$Y$1, 'Question context'!$E$2:$Y$49))} -> 2 | H17: High | I17: There is strong consensus (70â€“90) that this paper is highly relevant because it explicitly proposes a cooperative hierarchical distributed coordination architecture and motivates it by flexibility, scalability, and reduced communication burden versus centralized control. I kept the score high but not maximal because it does not comprehensively compare multiple aggregator/DSO-SO arrangements beyond its proposed architecture. | J17: There is a lot of synergy between the research paper abstract and the G-PST research question specifically - aggregation, control communications and broadly speaking DERs. Simulation results are also highlighted. There is a real sense of the linkages here on amethologcal basis between the G-PST research question and the paper abstract. | K17: The mention of microgrids in the ppaer abstract is a big reason that this paper abstract does not link more strongly with the G-PST research question. There are no indications that there are next steps to take this work further and apply with a system operator.
A18: 212 | B18: Comparative Analysis of the Power Output Capabilities of Grid-Following and Grid-Forming Inverters Considering Static, Dynamic, and Thermal Limitations | C18: =_xlfn.XLOOKUP(A18,'Abstracts List'!A:A,'Abstracts List'!C:C) -> This article investigates the maximum transferable power (MTP) of inverter-based resources (IBRs) and provides the output capability curves (OCCs) of grid-tied grid-following inverters (GFLIs) and grid-forming inverters (GFMIs). To this end, in the first part of the article, mathematical equations for GFLI static, thermal, and phase-locked loop (PLL)-induced power transfer limits are derived in terms of the grid short-circuit ratio (SCR) and its X/R ratio. Then, considering other operational limitations, such as the IBR AC- and DC-side voltage limits, the OCC of the GFLI is obtained. Additionally, the impact of the reactive current and the reactive control mode on the OCC is further studied, and accordingly, an auxiliary control loop is proposed to maximize the GFLI MTP. In the second part of the article, a similar approach is employed to derive mathematical equations for GFMI static and thermal limits, and accordingly, the OCC of a GFMI is obtained. The effects of the variation of the voltage set-point of the GFMI on its OCC are then studied, and the superiority of GFMIs compared to GFLIs is shown in terms of the MTP capability. Eventually, several simulation and experimental cases are conducted to validate the obtained equations and OCCs for both grid-following and grid-forming control modes. | D18: 9 | E18: What analytical tools and models should be provided to planners and operators for robust assessment of system performance in IBR-dominated power grids? | F18: Moderate | G18: {=_xlfn.XLOOKUP(D18, 'Question context'!$C$2:$C$49, _xlfn.XLOOKUP(A18, 'Question context'!$E$1:$Y$1, 'Question context'!$E$2:$Y$49))} -> 2 | H18: High | J18: The scope of the paper abstract and the G-PST research question share a lot in common. They are both driven by tools in the area of IBRs and their performance and capabilities. The paper abstract focusses on all types of IBRs which is showing reach and potential applicability. The paper mentions experimental cases which is indicative of applicability and it appaers there are multile cases which speaks t a potentially robust set of results. | K18: The link at the tools level may break down when real case studies are tackled. Additionally there is no mention of a real application and the paper is overly focussed on equations and not on realpractical results.
A19: 281 | B19: Minimum Energy Demands of Energy Storages for Fast Frequency Response: Formulation, Solution, and Implementation | C19: =_xlfn.XLOOKUP(A19,'Abstracts List'!A:A,'Abstracts List'!C:C) -> Energy storage (ES) is a kind of promising but costly fast-frequency-response (FFR) resource in low-inertia power systems. This article addresses the minimum demand of a power system for energy capacities of ES to providing sufficient frequency support, including the formulation, the optimal solution, and its practical implementation. First, the minimum energy control problem of ESs for providing FFR with transient frequency constraints is formulated and then converted into an optimal frequency trajectory planning counterpart. This transformation makes the transient frequency constraint tractable and allows to identify the optimal frequency trajectory that minimizes energy demand for ESs, which leads to an analytical expression of the system minimum demand for ESs energy capacities to ensure frequency security. Moreover, by unfolding the optimal frequency trajectory, the optimal control strategy of ESs is derived explicitly for the first time. The theoretical result directs to a practical controller implementation, which is referred to as the decentralized optimal energy frequency control (DOEFC). Finally, simulations on the modified IEEE 39-bus system verify our results and demonstrate the superiority of the DOEFC in reducing the energy capacity demand of ESs, defending successive disturbances, and hedging against parameter errors. | D19: 36 | E19: What system services can be designed to enable response from IBRs that can be a substitute for inertia (i.e. very fast frequency response)?Â Â | F19: Moderate | G19: {=_xlfn.XLOOKUP(D19, 'Question context'!$C$2:$C$49, _xlfn.XLOOKUP(A19, 'Question context'!$E$1:$Y$1, 'Question context'!$E$2:$Y$49))} -> 3 | H19: High | J19: Although the word services (and IBRs) do not appear in the abstract of the paper it is directed at fast frequency response (FFR) which is a service - hence it is linked with this G-pST research question. There are strong indications that applications are on their radar which is a positive. | K19: The paper abstract is a little too focussed on the fancy internal methods and not on the interesting results around fast frequency response as a service. Also no system operator is involved and the lack of a holistic type of approach that account sfor the multiple services required and their overlap is a shortcoming.
A20: 1 | B20: Scenario Reduction Network Based on Wasserstein Distance With Regularization | C20: =_xlfn.XLOOKUP(A20,'Abstracts List'!A:A,'Abstracts List'!C:C) -> Power systems with high penetration of renewable energy contain various uncertainties. Scenario-based optimization problems need a large number of discrete scenarios to obtain a reliable approximation for the probabilistic model. It is important to choose typical scenarios and ease the computational burden. This paper presents a scenario reduction network model based on Wasserstein distance. Entropy regularization is used to transform the scenario reduction problem into an unconstrained problem. Through an explicit neural network structure design, the output of the scenario reduction network corresponds to the Sinkhorn distance function. The scenario reduction network can generate the typical scenario set through unsupervised learning. An efficient algorithm is proposed for continuous/discrete scenario reduction. The superiority of the scenario reduction network model is verified through case studies. The numerical results highlight the high accuracy and computational efficiency of the proposed model over state-of-the-art models, and it makes an ideal candidate for large-scale scenario reduction problems. | D20: 42 | E20: What additional planning models and methods are needed to plan for various levels of uncertainty and no-regrets investments in a paradigm of increasing electrification and growing IBR and DER penetrations?Â | F20: Moderate | G20: {=_xlfn.XLOOKUP(D20, 'Question context'!$C$2:$C$49, _xlfn.XLOOKUP(A20, 'Question context'!$E$1:$Y$1, 'Question context'!$E$2:$Y$49))} -> 2 | H20: High | J20: The research reported in the abstract addresses the need for some sort of dimensionality reduction in order to deal with uncertainities which will arise in future power systems. thi sis a theme of the G-PST research question sin the planning research program. The paper proposes a method to do thi sreduction and this is aligned with the methodological scope of the research question. | K20: While there is a lot of alignment between the research question of the G-PST and the topic f the paper it is not clear if the research paper is developing the methods for application in planning which si the focus of the research question. There is also no sign that the work has a pathway to application with a system operator.
A21: 146 | B21: Automatic Generation of Topology Diagrams for Strongly-Meshed Power Transmission Systems | C21: =_xlfn.XLOOKUP(A21,'Abstracts List'!A:A,'Abstracts List'!C:C) -> Topology diagrams are widely seen in power system applications, but their automatic generation is often easier said than done. When facing power transmission systems with strongly-meshed structures, existing approaches can hardly produce topology diagrams catering to the aesthetics of readers. This paper proposes an integrated framework for generating aesthetically-pleasing topology diagrams for power transmission systems. Input with a rough layout, the framework first conducts visibility region analysis to reduce line crossings and then solves a mixed-integer linear programming problem to optimize the arrangement of nodes. Given that the complexity of both modules is pretty high, simplification heuristics are also proposed to enhance the efficiency of the framework. Case studies on several power transmission systems containing up to 2,046 nodes demonstrate the capability of the proposed framework in generating topology diagrams conforming to aesthetic criteria in the power system community. Compared with the widespread force-directed algorithm, the proposed framework can preserve the relative positions of nodes in the original layout to a great extent, which significantly contributes to the identification of electrical elements on the diagrams. Meanwhile, the time consumption is acceptable for practical applications. | D21: 26 | E21: What improvements can be made to predictive tools and visualization methodologies in operational applications within the control room to support decision-making in real-time operations? | F21: High | G21: {=_xlfn.XLOOKUP(D21, 'Question context'!$C$2:$C$49, _xlfn.XLOOKUP(A21, 'Question context'!$E$1:$Y$1, 'Question context'!$E$2:$Y$49))} -> 4 | H21: High | I21: There is strong cross-model agreement that the work directly improves visualization methodology for operational use by generating clearer, more readable topology diagrams that preserve relative positions and reduce crossings. Scores were moderated slightly below the highest values because the paper does not develop predictive tools and is not explicitly framed around real-time control-room deployment, but it is still highly relevant on the visualization side of the question. | J21: Very strong link between the abstract of the paper with its focus on presenting graphically information that the user can use and interpret. Practical application is a term used that is indicative that practical uses are being pursueed. The scale being quaoted at over 2000 nodes is good to see and looks like scaleability is very much in the minds of the researchers. Case studies are done on several systems which is indicative of robustness of the results. | K21: The actual title of the paper is not a good fit to the G-PST research agenda question but the abstract text is a good fit - hence reluctance to increase the score. There is no direct reference to control rooms which is a little concerning and there are no system operator stakeholders involved. There is alos more an emphasis on the algorithm side than on the user side and there is no mention of real time.

Sheet Rationale_clean
A1: Abstract_Index | B1: Abstract | C1: RA2025_ID | D1: Evaluator_Score | E1: Why this score was assigned to the abstract? | F1: Why does this abstract fall below the next relevance level? | G1: Changes Made
A2: =Rationale!A2 -> 65 | B2: =_xlfn.XLOOKUP(Rationale_clean!A2,'Abstracts List'!A:A,'Abstracts List'!G:G) -> the integration of numerous energy storage systems (esss) improves the reliable and economic operation of microgrids but also enlarges the burden of control and communication systems. this article proposes a cooperative hierarchical control for isolated microgrids with esss, which fully frees from the centralized paradigm and is therefore superior in flexibility and scalability. firstly, the ess cooperative control based on the distributed frequency controller is introduced for the state of charge (soc) balance and the frequency regulation. then, the ess aggregation is considered. the aggregated ess model is established and the real-time model parameters are derived by proposed distributed state observers. finally, energy management is employed to allocate the output power between generators and the aggregated ess. a detailed theoretical analysis of the dynamic and steady-state performance of proposed controllers and observers is provided. simulations on the ieee 33-bus and the 69-bus system verify the effectiveness of proposed methods. | C2: =Rationale!D2 -> 12 | D2: =Rationale!G2 -> 1 | E2: There are some potential links between the content of this abstract and the research question. In particular Microgrids can be considered to be DERs to some extent and by controlling them you are potentially making them somewhat like an aggregated DER resource. Some of the concepts like observability mentioned in the abstract are also potentially of interest. | F2: There is nothing direct within the abstract to link directly to aggregation and DERs. The links are at best second hand. The overall application of the abstract is on a test system not a real system and there is mention of the word theoretical which is not a confidence building term with respect to a real application. | G2: No changes. 'G-PST research question'→'research question': E2 (x1). Harmonized 'paper'/'research paper'→'abstract': E2 (x2), F2 (x2).
A3: =Rationale!A3 -> 94 | B3: =_xlfn.XLOOKUP(Rationale_clean!A3,'Abstracts List'!A:A,'Abstracts List'!G:G) -> with the increasing deployment of distributed energy resources (ders), dispatching ders subject to operational constraints in distribution networks draws much attention. one challenge is the non-convexities in 1) system-wide ac power flow constraints and 2) the individual complementarity constraint of energy storage. to resolve this challenge, this paper studies an ac-feasible linear model in distribution networks with energy storage, including its formulation, analysis, and applications. first, an ac-feasible linear model is formulated as a set of linear constraints on controllable ders and uncontrollable power demand by 1) converting the non-convex system-wide constraints into linear constraints based on the brouwers fixed-point theorem and the second-order taylor expansion, and 2) replacing the non-convex individual complementarity constraint of energy storage with one properly designed linear constraint. furthermore, to analyze the power demand level at which the proposed linear model can provide a solution, this paper proposes an examination-based projection method under the monte carlo framework to handle projections of thousands of dimensions from linear constraints over time periods. finally, the potential applications of our ac-feasible linear model are discussed. numerical experiments are conducted in the ieee 33-bus and 136-bus test systems to demonstrate the effectiveness of the proposed methods. | C3: =Rationale!D3 -> 13 | D3: =Rationale!G3 -> 1 | E3: There are some potential links between the content of this abstract and the research question. In particular this is about DERs and accounting for the constraints that DERs have - this is linked with the primary objective of the research question which is quantification of services and constraints in the distribution system are a key to understand that. There is also potential applications is mentioned in the abstract which is at least accepting application may be important. | F3: The focus of the abstract is on the distribution network and not the transmission network - in order for it to be scored higher it would need to focus on the transmission system. The abstract is very focussed on the details of the formulation of an optimisation problem and some theory and not on the formulation of a real applied problem. Test results are from a test system and not a real system with no obvious link to real industry stakeholders and/or real applications focussed work. | G3: Score rationale: 'constrainst'→'constraints', 'papaer'→'paper'. Below-level rationale: 'transmissio'→'transmission', 'it t be'→'it to be', 'prolem'→'problem', 'an real'→'a real', 'sysytem'→'system', 'obvius'→'obvious'. 'G-PST research question'→'research question': E3 (x2). Harmonized 'paper'→'abstract': E3 (x2), F3 (x2).
A4: =Rationale!A4 -> 194 | B4: =_xlfn.XLOOKUP(Rationale_clean!A4,'Abstracts List'!A:A,'Abstracts List'!G:G) -> proactive participation of uncertain renewable generation in the day-ahead (da) wholesale market effectively reduces the system marginal price and carbon emissions, whilst significantly increasing the volumes of real-time balancing mechanism prices to ensure system security and stability. to solve the conflicting interests over the two timescales, this article: 1) proposes a novel hierarchical optimization model to align with the actual operation paradigms of the hierarchical market, whereby the capacity allocation matrix is adopted to coordinate the da and balancing markets; 2) mathematically formulates and quantitatively analyses the long-term driving factors of balancing actions, enabling system operators (sos) to design efficient and well-functioning market structures to meet economic and environmental targets; 3) empowers renewable generating units and flexible loads to participate in the balancing market (bm) as active actors and enforces the non-discriminatory provision of balancing services. the performance of the proposed model is validated on a modified ieee 39-bus power system and a reduced gb network. results reveal that with effective resource allocation in different timescales of the hierarchical market, the drop speed of balancing costs soars while the intermittent generation climbs. the proposed methodology enables sos to make the most of all resources available in the market and balance the system flexibly and economically. it thus safeguards the climate mitigation pathways against the risks of substantially higher balancing costs. | C4: =Rationale!D4 -> 35 | D4: =Rationale!G4 -> 1 | E4: There are potential links between the abstract and the research question. In particular the abstract is addressing the British balancing market and the research question is asking can variable renewable energy provide services. The link if it is there is on the methods side. | F4: The potential links identified between the abstract and the research question are possibly misleading so scoring any higher is simply not justified. may not actually have anything of value | G4: Score rationale: 'british'→'British'. Below-level rationale: 'possibling'→'possibly'. Abstract: fixed corrupted quote characters (mojibake) around 'active'. 'G-PST research question'→'research question': E4 (x1), F4 (x1). Harmonized 'paper'→'abstract': E4 (x2), F4 (x1).
A5: =Rationale!A5 -> 44 | B5: =_xlfn.XLOOKUP(Rationale_clean!A5,'Abstracts List'!A:A,'Abstracts List'!G:G) -> when renewable energy-based generations are increasing, they are subject to cause frequency stability problems in a power system. to solve this problem, various virtual inertial control methods (vicms) have been recently developed. however, they all have dealt not with the steady-state frequency stability, but only with dynamic frequency stability issues. in particular, the wind power plants (wpps) operated by these vicms can only provide a similar inertial response (ir) to that by conventional synchronous generators without providing the primary frequency response (pfr). this results in lowering the settling frequency (sf) below the maximum steady-state frequency deviation (mssd) band. this paper proposes the new hierarchical control strategy for the wpps, which are operated by three virtual frequency response control methods (vfrcms) to provide both ir and pfr. firstly, the vfrcm-1 provides virtual ir. next, the vfrcm-2 increases the output power from the wpps to prevent the frequency drop, which can occur after the frequency nadir is arrested. finally, the vfrcm-3 makes the wpps possible to raise the sf above the mssd band by providing the virtual pfr. the effectiveness of proposed hierarchical control strategy is verified by several case studies on the ieee 39-bus test system with the high penetration of renewables. | C5: =Rationale!D5 -> 3 | D5: =Rationale!G5 -> 1 | E5: There is a potential link between the abstract which is focussed on controlling wind power plants to provide so called virtual frequency response and the research question which is focussed on the IBR control paradigm. The assumption is that IBR control and WPP control share a lot in common. | F5: The link identified may not result in any synergy between the research being reported in the abstract and the research question. While IBRs and WPPs do share some things in common the link in this instance may not actually amount to anything of interest. There is also no mention of any real application or involvement of system operators and industry and the results are on a test system not a real system. | G5: Score rationale: 'astract'→'abstract'. 'G-PST research question'→'research question': E5 (x1), F5 (x1). Harmonized 'paper'→'abstract': E5 (x1), F5 (x1).
A6: =Rationale!A6 -> 81 | B6: =_xlfn.XLOOKUP(Rationale_clean!A6,'Abstracts List'!A:A,'Abstracts List'!G:G) -> the deployment of prosumers with distributed energy resources (ders) has facilitated the prosumer-centric transactive market, giving rise to the consequent necessity for the coordination between prosumers and the distribution networks. this paper proposes an incentive-based expansion planning method considering virtual peer-to-peer (p2p) transaction among prosumers, which is characterized as a tri-level planning-operation-transaction framework. each prosumer optimizes its internal response of ders and external p2p transaction jointly, formulating virtual p2p transaction. under such a paradigm, the distribution company (disco) identifies the optimal expansion planning in the network assets, while the independent distribution system operator (idso) is responsible for the optimal operation of the expanded distribution networks. to derive appropriate incentives for each prosumer, the disco and idso allocate long-term investment network charges and short-term operation network charges on prosumers, along with the designed financial transmission rights coupling multiple time scales. through such incentives, self-profit driven virtual transactions can relieve operation problems and postpone expansion planning, acting as a short-term alternative. moreover, a risk-based approach is proposed for prosumer to flexibly change strategy according to different risk preference. finally, results from the case study demonstrate the superiority and effectiveness of the proposed method in the collaborative application of virtual transaction in the expansion planning. | C6: =Rationale!D6 -> 13 | D6: =Rationale!G6 -> 1 | E6: DERs and one of the stakeholders the prosumer are identified in the abstract which has potential links to quantification of services from DERs and sharing of these among other stakeholders. | F6: The identified research question is in the services area yet the abstract is tackling a planning problem so the links identified are at best tangential and at worst non existent. The whole area of transactive energy and markets is out of scope for research question so that is a poor indicator of strong links. The application domain and/or time frame of the abstract and the research question may differ it looks like the abstract is targeting planning while the research question is in the operations time frame. | G6: Score rationale: 'abstact'→'abstract', 'papaer'→'paper', 'frm'→'from', 'amoung'→'among'. Below-level rationale: 'plannig'→'planning', 'loks'→'looks', 'i sin'→'is in'. Document Title: fixed corrupted apostrophe (mojibake) in 'Prosumers''. 'G-PST research question'→'research question': F6 (x4). Harmonized 'paper'→'abstract': E6 (x1), F6 (x3).
A7: =Rationale!A7 -> 241 | B7: =_xlfn.XLOOKUP(Rationale_clean!A7,'Abstracts List'!A:A,'Abstracts List'!G:G) -> accurate wind power forecast (wpf) is critical for ensuring secure and economic operation of a power system, and combination forecasting approaches for wpf have been proved effective on attaining accurate forecasting results. however, the weights in a combination forecasting model are usually predetermined based on the global performance on the training set, limiting the adaptability of the model to different scenarios. to further enhance the accuracy and effectiveness of the combination forecasting approaches, this article proposes an adaptive weighted combination forecasting approach based on the deep deterministic policy gradient (ddpg) so as to consider the local behavior accompanied by the change of external environment. three sub-models are first selected considering the equal-likelihood and dispersion indices to construct a combination model. then, the ddpg agent is trained to act as a weight generator by interacting with the environment and to maximize the reward. thus, the ddpg agent can perceive the environmental changes online and dynamically weight the sub-models to attain accurate forecasting results. case studies demonstrate that the forecasting accuracy of the proposed approach is better than that of all sub-models and several benchmark combination forecasting approaches. | C7: =Rationale!D7 -> 27 | D7: =Rationale!G7 -> 1 | E7: This is an incremental piece of research that does not directly address any of the research questions but does potentially have some links to some aspects of the research agenda. | F7: There are no real practical applications. It is mainly methodological and incremental and it is at best a small potential contribution to a very secondary aspect of the much more impactful research question. | G7: Score rationale: 'and of'→'any of', 'paotentially'→'potentially'. Below-level rationale: 'methological'→'methodological'. 'G-PST research questions'→'research questions': E7 (x1).
A8: =Rationale!A8 -> 94 | B8: =_xlfn.XLOOKUP(Rationale_clean!A8,'Abstracts List'!A:A,'Abstracts List'!G:G) -> with the increasing deployment of distributed energy resources (ders), dispatching ders subject to operational constraints in distribution networks draws much attention. one challenge is the non-convexities in 1) system-wide ac power flow constraints and 2) the individual complementarity constraint of energy storage. to resolve this challenge, this paper studies an ac-feasible linear model in distribution networks with energy storage, including its formulation, analysis, and applications. first, an ac-feasible linear model is formulated as a set of linear constraints on controllable ders and uncontrollable power demand by 1) converting the non-convex system-wide constraints into linear constraints based on the brouwers fixed-point theorem and the second-order taylor expansion, and 2) replacing the non-convex individual complementarity constraint of energy storage with one properly designed linear constraint. furthermore, to analyze the power demand level at which the proposed linear model can provide a solution, this paper proposes an examination-based projection method under the monte carlo framework to handle projections of thousands of dimensions from linear constraints over time periods. finally, the potential applications of our ac-feasible linear model are discussed. numerical experiments are conducted in the ieee 33-bus and 136-bus test systems to demonstrate the effectiveness of the proposed methods. | C8: =Rationale!D8 -> 12 | D8: =Rationale!G8 -> 1 | E8: There may be some potential link between the research as described in the abstract and the research question. This link is embodied in the focus on DERs in both the abstract and the research question but the link is at best tenuous. | F8: An incremental piece of research is reported in the abstract and it is not directly related to the research question. It is also fixated on methodology and only conducts some numerical experiments with no sign of a real application. | G8: Score rationale: 'DErs'→'DERs', 'tenous'→'tenuous'. 'G-PST research question'→'research question': E8 (x1), F8 (x1). Harmonized 'paper'→'abstract': E8 (x1), F8 (x1).
A9: =Rationale!A9 -> 45 | B9: =_xlfn.XLOOKUP(Rationale_clean!A9,'Abstracts List'!A:A,'Abstracts List'!G:G) -> this paper proposes a new time aggregation method that can properly reflect the spatial aspect of the data sources alongside their temporal behaviour when multiple variable energy resources are involved. each representative period, constructed by the proposed method, can include more than one representative day, which, in itself, represents a group of data sources that are highly associated with each other. it also preserves the spatial relationship among data sources as a whole by constructing a hybrid centroid. two case studies, each with different data sources and networks, with and without energy storage, are considered for this study. in the second case, we add an storage to reflect the significance of preserving shape of patterns in the representative periods. the duration curves of wind farms and solar farms generations, electricity demand, and net demand are used as data-based evaluation indices to compare the performance of the proposed method against other approaches. in addition, an ieee 24-bus and a 6-bus test system are considered for the case studies. two model-based evaluation indices are used to measure the performance of the clustering methods, including the power flow of all the lines in the system and the annual operation cost of the system. in addition, the performance of the proposed method in the presence of energy storage is evaluated and compared with existing methods. | C9: =Rationale!D9 -> 12 | D9: =Rationale!G9 -> 1 | E9: This is a methods based abstract that has some small potential link to the research agenda. The research question is seeking methods to use when trying to account for DERs in planning and techno economic analysis and this abstract may be useful when dealing with aggregation of the spatial /DER aspects. | F9: This is an abstract with a potential link to some aspects of the G-PST research agenda in the DER space. It shares data and aggregation of variable renewable energy within the scope of the abstract. It is at best an incremental contribution and has only some small case studies that are not obviously directly related to the research agenda. | G9: Score rationale: 'econmic'→'economic'. Below-level rationale: 'an potential'→'a potential', 'icremental'→'incremental'. Harmonized 'paper'→'abstract': E9 (x2), F9 (x2).
A10: =Rationale!A10 -> 228 | B10: =_xlfn.XLOOKUP(Rationale_clean!A10,'Abstracts List'!A:A,'Abstracts List'!G:G) -> deep penetration of distributed energy resources (ders) and electric vehicles (evs) introduce benefits but may cause the overloading of service transformers in distribution networks. such situations require real-time transformer loading information, where an accurate mapping between smart meters and distribution transformers is a prerequisite, e.g., summing the downstream smart meter consumptions. due to arbitrary curvature in streets, we propose to employ a density-based clustering based on voltage magnitudes (continuous) and street name (categorical) information. however, a density-based approach may only be able to localize a meter to a street segment. hence, we use a second-stage spectral clustering with distance along the street (das), a novel feature, to obtain meter clusters, each with a common parent transformer. for mapping transformers to meter clusters, we use the nearest cluster center approach based on the location since voltage measurements may not be available at transformers. moreover, we provide a theoretical guarantee for such an approach. finally, we illustrate the usefulness of the proposed algorithm on long streets, which is a challenging scenario due to many possible incorrect combinations of meter-transformer mapping. the proposed algorithm has been tested on modified ieee 8-, 69-, 123-bus test systems and real distribution feeders from a utility in the southwestern united states, demonstrating outstanding performance. | C10: =Rationale!D10 -> 15 | D10: =Rationale!G10 -> 1 | E10: This abstract addresses a distribution level challenge that can have some impact on the higher level transmission related problems that are the focus of the G-PST research agenda. It does however have a good potential link to a real practical problem as indicated by the real distribution utility application. | F10: The abstract does not address a research question in any direct way - it is focussed on the distribution system and not the transmission system therefore its link to the research question is minimal. While there is an application in the abstract it is not on the transmission system so that is a big weakness with respect to a strong link with the research question. | G10: Score rationale: 'pratctical'→'practical', 'untility'→'utility'. Below-level rationale: 'ppaer'→'paper' (x2), 'in and direct'→'in any direct', 'resect'→'respect'. Abstract: removed LaTeX artifact '$6{9}$'→'69'. 'G-PST research question'→'research question': F10 (x3). Harmonized 'paper'→'abstract': E10 (x1), F10 (x2, incl. 'The paper aspect'→'The abstract').
A11: =Rationale!A11 -> 134 | B11: =_xlfn.XLOOKUP(Rationale_clean!A11,'Abstracts List'!A:A,'Abstracts List'!G:G) -> power system congestion event prognosis (cep) based on multivariate time series (mts) learning is an effective way to improve the warning abilities against risky situations. however, it is still challenging to decide which measurement sequences of system variables should be selected to train mts learning-based ceps models, especially when facing high-dimensional candidate features from power systems. focusing on this issue, this paper proposes a novel high-dimensional feature selection (fs) method to identify and select variables that contain beneficial data patterns for the prognosis of network congestion events. a wrapper framework embedded with multiple mts learning models is first built to treat fs as a combinatorial optimization task and receive mts as inputs directly without sequence compressions. then, to improve the combinatorial optimization efficiency and fs results in the high-dimensional case, a hybrid structure called enhanced evolutionary computation (eec) is developed by combining with information theory-based feature priority scores, which play the role of semi-guidance in the iterative search. test results on both the real-world and synthetic datasets validate the effectiveness of the developed eec structure and show that the selected features by the proposed fs method are more beneficial in identifying the early patterns of network congestion events, thus contributing to efficient and accurate cep for power systems. | C11: =Rationale!D11 -> 21 | D11: =Rationale!G11 -> 2 | E11: The research in this abstract has a reasonably good link to the research question. The abstract describes a method to identify features that can be used to enhance the potential of harnessing flexibility resources. There is reference to a real world test results which is encouraging. | F11: While the links are potentially strong between the abstract and the research question they are not direct. The abstract addresses congestion but the research question is focussed on flexibility - congestion has an impact of flexibility but is not a one to one relationship. No clear link or working relationship with a system operator is evident. | G11: Below-level rationale: 'paer'→'paper', 'i snot'→'is not', 'oneto'→'one to'. 'G-PST research question'→'research question': E11 (x1). Harmonized 'paper'→'abstract': E11 (x2), F11 (x2).
A12: =Rationale!A12 -> 231 | B12: =_xlfn.XLOOKUP(Rationale_clean!A12,'Abstracts List'!A:A,'Abstracts List'!G:G) -> coordinated dispatch of integrated transmission-distribution systems (itds) continues to be a hotspot due to the growing demand-side flexibility. decentralized optimization, which has been widely studied, does not conform to the current hierarchical framework of power system operation. this paper proposes a centralized distributionally robust chance-constrained dispatch model for itds. the transmission system operator considers the flexible ranges of large-scale distributed energy resources (ders) in distribution systems via flexibility aggregation. a price-guided flexibility model is proposed to describe the temporally coupled aggregate flexibility of distribution systems. it is constructed by filtering those constraints with a high probability of activeness in the itd dispatch problem, reducing the number of constraints from quadratic to linear with the number of divided time slots while maintaining high accuracy. furthermore, we use the data-driven distributionally robust chance constraint to deal with the uncertainty from both renewable generations and the flexibility of ders. numerical simulations on ieee test systems verify the effectiveness of the proposed methods. | C12: =Rationale!D12 -> 39 | D12: =Rationale!G12 -> 2 | E12: There is a potential relationship between the focus of the abstract and the G-PST research agenda. The abstract focusses on the transmission distribution interface which is important in the DER part of the research agenda and the specific research question is looking into how reliability services in planning can account for deliverability. | F12: The research in the abstract only relates to a small part of the research question and there are no signs of real practical application. It is also not clear if the abstract can provide real planning related benefits as it is really focussed on operations so more work would need to be done to bring this research in the abstract closer to the practical research question. | G12: Score rationale: 'relationshio'→'relationship'. Below-level rationale: 'ppaer'→'paper', 'te practical'→'the practical'. 'G-PST research question'→'research question': F12 (x1). Harmonized 'paper'→'abstract': E12 (x2), F12 (x3).
A13: =Rationale!A13 -> 212 | B13: =_xlfn.XLOOKUP(Rationale_clean!A13,'Abstracts List'!A:A,'Abstracts List'!G:G) -> this article investigates the maximum transferable power (mtp) of inverter-based resources (ibrs) and provides the output capability curves (occs) of grid-tied grid-following inverters (gflis) and grid-forming inverters (gfmis). to this end, in the first part of the article, mathematical equations for gfli static, thermal, and phase-locked loop (pll)-induced power transfer limits are derived in terms of the grid short-circuit ratio (scr) and its x/r ratio. then, considering other operational limitations, such as the ibr ac- and dc-side voltage limits, the occ of the gfli is obtained. additionally, the impact of the reactive current and the reactive control mode on the occ is further studied, and accordingly, an auxiliary control loop is proposed to maximize the gfli mtp. in the second part of the article, a similar approach is employed to derive mathematical equations for gfmi static and thermal limits, and accordingly, the occ of a gfmi is obtained. the effects of the variation of the voltage set-point of the gfmi on its occ are then studied, and the superiority of gfmis compared to gflis is shown in terms of the mtp capability. eventually, several simulation and experimental cases are conducted to validate the obtained equations and occs for both grid-following and grid-forming control modes. | C13: =Rationale!D13 -> 4 | D13: =Rationale!G13 -> 2 | E13: Thematically the abstract aligns very well with the IBR research program of the G-PST research agenda and specifically the research reported in this abstract addresses capability and control design. It also deals with these issues across the range of IBRs i.e. GFM and GFL. The focus of the abstract is in addressing real issues and is not methodologically dominated which is another good sign. | F13: The abstract stops short of services and/or operational decision making which limits its potential linkage to the research question. Although simulation results and experiments are noted it is not clear if they are at the right scale and applicability to be truly useful nor is it clear if a utility and/or a system operator are involved. | G13: Score rationale: 'ths'→'this', 'accross'→'across'. Below-level rationale: 'stpos'→'stops', 'deceson'→'decision', 'G-pST'→'G-PST', 'i snot'→'is not'. 'G-PST research question'→'research question': F13 (x1). Harmonized 'paper'→'abstract': E13 (x3), F13 (x1).
A14: =Rationale!A14 -> 44 | B14: =_xlfn.XLOOKUP(Rationale_clean!A14,'Abstracts List'!A:A,'Abstracts List'!G:G) -> when renewable energy-based generations are increasing, they are subject to cause frequency stability problems in a power system. to solve this problem, various virtual inertial control methods (vicms) have been recently developed. however, they all have dealt not with the steady-state frequency stability, but only with dynamic frequency stability issues. in particular, the wind power plants (wpps) operated by these vicms can only provide a similar inertial response (ir) to that by conventional synchronous generators without providing the primary frequency response (pfr). this results in lowering the settling frequency (sf) below the maximum steady-state frequency deviation (mssd) band. this paper proposes the new hierarchical control strategy for the wpps, which are operated by three virtual frequency response control methods (vfrcms) to provide both ir and pfr. firstly, the vfrcm-1 provides virtual ir. next, the vfrcm-2 increases the output power from the wpps to prevent the frequency drop, which can occur after the frequency nadir is arrested. finally, the vfrcm-3 makes the wpps possible to raise the sf above the mssd band by providing the virtual pfr. the effectiveness of proposed hierarchical control strategy is verified by several case studies on the ieee 39-bus test system with the high penetration of renewables. | C14: =Rationale!D14 -> 4 | D14: =Rationale!G14 -> 2 | E14: This abstract describes research that directly addresses the capability of wind plant to provide frequency control services. It also directly addresses the control problem and there are case studies on a test network. These are all indicative of a solid link with the research question. | F14: The abstract falls short of being strongly linked to the research question as it does not appear to be directed fully at the IBR aspects and it is also very focussed on the device rather than on the system itself. Furthermore the case study is on a small typical test network and there does not appear to be any system operator involvement and/or any practical insights reported in the results. | G14: Score rationale: 'a a test'→'a test', 'lin'→'link'. Below-level rationale: 'appaer'→'appear' (x2), 'i son'→'is on'. 'G-PST research question'→'research question': E14 (x1), F14 (x1). Harmonized 'paper'→'abstract': E14 (x1), F14 (x1).
A15: =Rationale!A15 -> 174 | B15: =_xlfn.XLOOKUP(Rationale_clean!A15,'Abstracts List'!A:A,'Abstracts List'!G:G) -> increased penetration of renewable resources and new loads have increased the uncertainty levels in low voltage distribution systems (lvds). this requires considering lvds planning, such as computing photovoltaics (pv) hosting capacity (hc), as a stochastic problem. traditionally, pv hc is computed using the iterative monte carlo method, which requires solving the power flow equations thousands of times. this paper proposes a chance-constrained optimization-based hosting capacity calculation technique, which eliminates the necessity of repetitive solving of power flow equations. the intrusive general polynomial chaos expansion is used to translate the input uncertainties defined by their probability density function to the hosting capacity of the network without the necessity of sampling, linearizing the power flow equations, or applying any relaxations. chance constraints are applied for nodal voltages and thermal overload as per the norms, where the system can be congested for a certain time without affecting the power quality. numerical illustrations show the computational time to compute the stochastic pv hosting capacity of a real large scale lvds, and for the majority of the feeders, it falls within 100 sec. furthermore, the estimated pv hc using this stochastic optimal power flow was, on average, 20% higher than its deterministic counterpart. | C15: =Rationale!D15 -> 42 | D15: =Rationale!G15 -> 2 | E15: While there is good alignment from a methods perspective the practical application of the research may only be on the distribution network which may limit the research work being reported in the abstract with respect to the G-PST transmission system perspective and scope. There is also no sign of a real practical result and a path towards deployment of the research to system operators. | G15: Score rationale: 'papaer'→'paper', 'transmssion'→'transmission', 'towrads'→'towards'. Harmonized 'paper'→'abstract': E15 (x1).
A16: =Rationale!A16 -> 134 | B16: =_xlfn.XLOOKUP(Rationale_clean!A16,'Abstracts List'!A:A,'Abstracts List'!G:G) -> power system congestion event prognosis (cep) based on multivariate time series (mts) learning is an effective way to improve the warning abilities against risky situations. however, it is still challenging to decide which measurement sequences of system variables should be selected to train mts learning-based ceps models, especially when facing high-dimensional candidate features from power systems. focusing on this issue, this paper proposes a novel high-dimensional feature selection (fs) method to identify and select variables that contain beneficial data patterns for the prognosis of network congestion events. a wrapper framework embedded with multiple mts learning models is first built to treat fs as a combinatorial optimization task and receive mts as inputs directly without sequence compressions. then, to improve the combinatorial optimization efficiency and fs results in the high-dimensional case, a hybrid structure called enhanced evolutionary computation (eec) is developed by combining with information theory-based feature priority scores, which play the role of semi-guidance in the iterative search. test results on both the real-world and synthetic datasets validate the effectiveness of the developed eec structure and show that the selected features by the proposed fs method are more beneficial in identifying the early patterns of network congestion events, thus contributing to efficient and accurate cep for power systems. | C16: =Rationale!D16 -> 23 | D16: =Rationale!G16 -> 2 | E16: The focus of the abstract on feature selection and training using large data sets is very well aligned with the underlying research question being asked for in the G-PST research agenda research question. Real world data along with synthetic data is also used in the abstract. | F16: While at a basic level the abstract describes research that looks at large complex data sets to help in power system operations the focus of the abstract is only on one aspect, congestion and there is also no sign that multiple time scales are addressed. Therefore the abstract is potentially well linked with a very specific aspect of the research question but not the holistic aspects. No practical next steps are identified nor is there any sign of a real system operator and/or industry partner. | G16: Below-level rationale: 'G-PSt'→'G-PST', 'resarch'→'research'. 'G-PST research question'→'research question': F16 (x1). Harmonized 'paper'→'abstract': E16 (x2), F16 (x3).
A17: =Rationale!A17 -> 65 | B17: =_xlfn.XLOOKUP(Rationale_clean!A17,'Abstracts List'!A:A,'Abstracts List'!G:G) -> the integration of numerous energy storage systems (esss) improves the reliable and economic operation of microgrids but also enlarges the burden of control and communication systems. this article proposes a cooperative hierarchical control for isolated microgrids with esss, which fully frees from the centralized paradigm and is therefore superior in flexibility and scalability. firstly, the ess cooperative control based on the distributed frequency controller is introduced for the state of charge (soc) balance and the frequency regulation. then, the ess aggregation is considered. the aggregated ess model is established and the real-time model parameters are derived by proposed distributed state observers. finally, energy management is employed to allocate the output power between generators and the aggregated ess. a detailed theoretical analysis of the dynamic and steady-state performance of proposed controllers and observers is provided. simulations on the ieee 33-bus and the 69-bus system verify the effectiveness of proposed methods. | C17: =Rationale!D17 -> 18 | D17: =Rationale!G17 -> 2 | E17: There is a lot of synergy between the abstract and the research question specifically - aggregation, control communications and broadly speaking DERs. Simulation results are also highlighted. There is a real sense of the linkages here on a methodological basis between the research question and the abstract. | F17: The mention of microgrids in the abstract is a big reason that this abstract does not link more strongly with the research question. There are no indications that there are next steps to take this work further and apply with a system operator. | G17: E17: "amethologcal" corrected to "a methodological". F17: "ppaer" corrected to "paper". 'G-PST research question'→'research question': E17 (x2), F17 (x1). Harmonized 'paper'→'abstract': E17 (x2), F17 (x2).
A18: =Rationale!A18 -> 212 | B18: =_xlfn.XLOOKUP(Rationale_clean!A18,'Abstracts List'!A:A,'Abstracts List'!G:G) -> this article investigates the maximum transferable power (mtp) of inverter-based resources (ibrs) and provides the output capability curves (occs) of grid-tied grid-following inverters (gflis) and grid-forming inverters (gfmis). to this end, in the first part of the article, mathematical equations for gfli static, thermal, and phase-locked loop (pll)-induced power transfer limits are derived in terms of the grid short-circuit ratio (scr) and its x/r ratio. then, considering other operational limitations, such as the ibr ac- and dc-side voltage limits, the occ of the gfli is obtained. additionally, the impact of the reactive current and the reactive control mode on the occ is further studied, and accordingly, an auxiliary control loop is proposed to maximize the gfli mtp. in the second part of the article, a similar approach is employed to derive mathematical equations for gfmi static and thermal limits, and accordingly, the occ of a gfmi is obtained. the effects of the variation of the voltage set-point of the gfmi on its occ are then studied, and the superiority of gfmis compared to gflis is shown in terms of the mtp capability. eventually, several simulation and experimental cases are conducted to validate the obtained equations and occs for both grid-following and grid-forming control modes. | C18: =Rationale!D18 -> 9 | D18: =Rationale!G18 -> 2 | E18: The scope of the abstract and the research question share a lot in common. They are both driven by tools in the area of IBRs and their performance and capabilities. The abstract focusses on all types of IBRs which is showing reach and potential applicability. The abstract mentions experimental cases which is indicative of applicability and it appears there are multiple cases which speaks to a potentially robust set of results. | F18: The link at the tools level may break down when real case studies are tackled. Additionally there is no mention of a real application and the abstract is overly focussed on equations and not on real practical results. | G18: Score rationale: 'appaers'→'appears', 'multile'→'multiple', 'speaks t a'→'speaks to a'. Below-level rationale: 'realpractical'→'real practical'. 'G-PST research question'→'research question': E18 (x1). Harmonized 'paper'→'abstract': E18 (x3), F18 (x1).
A19: =Rationale!A19 -> 281 | B19: =_xlfn.XLOOKUP(Rationale_clean!A19,'Abstracts List'!A:A,'Abstracts List'!G:G) -> energy storage (es) is a kind of promising but costly fast-frequency-response (ffr) resource in low-inertia power systems. this article addresses the minimum demand of a power system for energy capacities of es to providing sufficient frequency support, including the formulation, the optimal solution, and its practical implementation. first, the minimum energy control problem of ess for providing ffr with transient frequency constraints is formulated and then converted into an optimal frequency trajectory planning counterpart. this transformation makes the transient frequency constraint tractable and allows to identify the optimal frequency trajectory that minimizes energy demand for ess, which leads to an analytical expression of the system minimum demand for ess energy capacities to ensure frequency security. moreover, by unfolding the optimal frequency trajectory, the optimal control strategy of ess is derived explicitly for the first time. the theoretical result directs to a practical controller implementation, which is referred to as the decentralized optimal energy frequency control (doefc). finally, simulations on the modified ieee 39-bus system verify our results and demonstrate the superiority of the doefc in reducing the energy capacity demand of ess, defending successive disturbances, and hedging against parameter errors. | C19: =Rationale!D19 -> 36 | D19: =Rationale!G19 -> 3 | E19: Although the word services (and IBRs) do not appear in the abstract it is directed at fast frequency response (FFR) which is a service - hence it is linked with this research question. There are strong indications that applications are on their radar which is a positive. | F19: The abstract is a little too focussed on the fancy internal methods and not on the interesting results around fast frequency response as a service. Also no system operator is involved and the lack of a holistic type of approach that accounts for the multiple services required and their overlap is a shortcoming. | G19: E19: "G-pST" corrected to "G-PST". F19: "account sfor" corrected to "accounts for". 'G-PST research question'→'research question': E19 (x1). Harmonized 'paper'→'abstract': E19 (x1), F19 (x1).
A20: =Rationale!A20 -> 1 | B20: =_xlfn.XLOOKUP(Rationale_clean!A20,'Abstracts List'!A:A,'Abstracts List'!G:G) -> power systems with high penetration of renewable energy contain various uncertainties. scenario-based optimization problems need a large number of discrete scenarios to obtain a reliable approximation for the probabilistic model. it is important to choose typical scenarios and ease the computational burden. this paper presents a scenario reduction network model based on wasserstein distance. entropy regularization is used to transform the scenario reduction problem into an unconstrained problem. through an explicit neural network structure design, the output of the scenario reduction network corresponds to the sinkhorn distance function. the scenario reduction network can generate the typical scenario set through unsupervised learning. an efficient algorithm is proposed for continuous/discrete scenario reduction. the superiority of the scenario reduction network model is verified through case studies. the numerical results highlight the high accuracy and computational efficiency of the proposed model over state-of-the-art models, and it makes an ideal candidate for large-scale scenario reduction problems. | C20: =Rationale!D20 -> 42 | D20: =Rationale!G20 -> 2 | E20: The research reported in the abstract addresses the need for some sort of dimensionality reduction in order to deal with uncertainties which will arise in future power systems. This is a theme of the research questions in the planning research program. The abstract proposes a method to do this reduction and this is aligned with the methodological scope of the research question. | F20: While there is a lot of alignment between the research question of the G-PST and the topic of the abstract it is not clear if the abstract is developing the methods for application in planning which is the focus of the research question. There is also no sign that the work has a pathway to application with a system operator. | G20: Score rationale: 'uncertainities'→'uncertainties', 'thi sis'→'This is', 'question sin'→'questions in', 'thi sreduction'→'this reduction'. Below-level rationale: 'topic f'→'topic of', 'which si'→'which is'. 'G-PST research questions'→'research questions': E20 (x1). Harmonized 'paper'→'abstract': E20 (x1), F20 (x2).
A21: =Rationale!A21 -> 146 | B21: =_xlfn.XLOOKUP(Rationale_clean!A21,'Abstracts List'!A:A,'Abstracts List'!G:G) -> topology diagrams are widely seen in power system applications, but their automatic generation is often easier said than done. when facing power transmission systems with strongly-meshed structures, existing approaches can hardly produce topology diagrams catering to the aesthetics of readers. this paper proposes an integrated framework for generating aesthetically-pleasing topology diagrams for power transmission systems. input with a rough layout, the framework first conducts visibility region analysis to reduce line crossings and then solves a mixed-integer linear programming problem to optimize the arrangement of nodes. given that the complexity of both modules is pretty high, simplification heuristics are also proposed to enhance the efficiency of the framework. case studies on several power transmission systems containing up to 2,046 nodes demonstrate the capability of the proposed framework in generating topology diagrams conforming to aesthetic criteria in the power system community. compared with the widespread force-directed algorithm, the proposed framework can preserve the relative positions of nodes in the original layout to a great extent, which significantly contributes to the identification of electrical elements on the diagrams. meanwhile, the time consumption is acceptable for practical applications. | C21: =Rationale!D21 -> 26 | D21: =Rationale!G21 -> 4 | E21: Very strong link between the abstract with its focus on presenting graphically information that the user can use and interpret. Practical application is a term used that is indicative that practical uses are being pursued. The scale being quoted at over 2000 nodes is good to see and looks like scalability is very much in the minds of the researchers. Case studies are done on several systems which is indicative of robustness of the results. | F21: The actual title of the abstract is not a good fit to the research question but the abstract text is a good fit - hence reluctance to increase the score. There is no direct reference to control rooms which is a little concerning and there are no system operator stakeholders involved. There is also more an emphasis on the algorithm side than on the user side and there is no mention of real time. | G21: Score rationale: 'pursueed'→'pursued', 'quaoted'→'quoted', 'scaleability'→'scalability'. Below-level rationale: 'alos'→'also'. 'G-PST research agenda question'→'research question': F21 (x1). Harmonized 'paper'→'abstract': E21 (x1), F21 (x1).

Sheet Question Detail
A1: Section | B1: Question | C1: Questions Group | D1: Groupings | E1: Question | F1: Role | H1: New # | I1: List | K1: Question | L1: Question Long
A2: IBR | B2: 1 | C2: I.1 | D2: Power system evolution with high IBR shares | E2: Future of MW balance in low-inertia power systems | F2: Core | H2: =B2&" - "& _xlfn.XLOOKUP(B2,$K$2:$K$49,$L$2:$L$49) -> 1 - What is the future of active power balance as the synchronous generation fraction reduces? For example, might tightened or loosened frequency (or similar proxy for active power balance) limits lead to a more reliable, secure, lower-cost IBR-based power system? | I2: IBR | K2: 1 | L2: What is the future of active power balance as the synchronous generation fraction reduces? For example, might tightened or loosened frequency (or similar proxy for active power balance) limits lead to a more reliable, secure, lower-cost IBR-based power system?
A3: IBR | B3: 2 | C3: I.1 | D3: Power system evolution with high IBR shares | E3: New protection systems for high IBR penetration | F3: Core | H3: =B3&" - "& _xlfn.XLOOKUP(B3,$K$2:$K$49,$L$2:$L$49) -> 2 - How will protection systems need to change to accommodate high penetrations of IBRs, and what possible actions might an inverter take during a fault that would help fault detection and location? | I3: Stability | K3: 2 | L3: How will protection systems need to change to accommodate high penetrations of IBRs, and what possible actions might an inverter take during a fault that would help fault detection and location?
A4: IBR | B4: 3 | C4: I.1 | D4: Power system evolution with high IBR shares | E4: Point to exploit wider flexibility and stop SM replication | F4: Core | H4: =B4&" - "& _xlfn.XLOOKUP(B4,$K$2:$K$49,$L$2:$L$49) -> 3 - How could the IBR control paradigm change from replicating synchronous machines to exploiting wider IBR flexibility without introducing integration challenges during the transition? | I4: DER_CC | K4: 3 | L4: How could the IBR control paradigm change from replicating synchronous machines to exploiting wider IBR flexibility without introducing integration challenges during the transition?
A5: IBR | B5: 4 | C5: I.2 | D5: IBR design standards and capabilities | E5: Appropriate inverter capabilities | F5: Core | H5: =B5&" - "& _xlfn.XLOOKUP(B5,$K$2:$K$49,$L$2:$L$49) -> 4 - What are the appropriate inverter capabilities and, consequently, control design methods for operation in grids with high percentages of IBRs, and are standard configurations and combinations of services helpful in simplifying operational decision-making? | I5: DER_Services | K5: 4 | L5: What are the appropriate inverter capabilities and, consequently, control design methods for operation in grids with high percentages of IBRs, and are standard configurations and combinations of services helpful in simplifying operational decision-making?
A6: IBR | B6: 5 | C6: I.2 | D6: IBR design standards and capabilities | E6: Standard behaviors of IBRs in certain freq. ranges | F6: Core | H6: =B6&" - "& _xlfn.XLOOKUP(B6,$K$2:$K$49,$L$2:$L$49) -> 5 - What recommendations for standard IBR frequency characteristics and responses should be identified to help system design? For example, should a contribution to damping be mandatory at certain frequencies? | I6: CROF | K6: 5 | L6: What recommendations for standard IBR frequency characteristics and responses should be identified to help system design? For example, should a contribution to damping be mandatory at certain frequencies?
A7: IBR | B7: 6 | C7: I.2 | D7: IBR design standards and capabilities | E7: Impedance requirements on IBR to control negative sequence | F7: Core | H7: =B7&" - "& _xlfn.XLOOKUP(B7,$K$2:$K$49,$L$2:$L$49) -> 6 - What requirements (e.g. impedance) should be placed on IBRs to control negative sequence currents for protection and harmonics suppression? | I7: Services | K7: 6 | L7: What requirements (e.g. impedance) should be placed on IBRs to control negative sequence currents for protection and harmonics suppression?
